Workbook

Sheet Dashboard
B1: DATA INTELLIGENCE DASHBOARD
B2: ="Customer transactions | "&TEXT(Analysis!B8,"dd mmm yyyy")&" to "&TEXT(Analysis!B9,"dd mmm yyyy")&" | "&Analysis!B25&" orders | Refreshed "&TEXT(NOW(),"dd mmm yyyy hh:mm") -> Customer transactions | 11 Apr 2024 to 11 Apr 2025 | 250 orders | Refreshed 23 Oct 2026 15:33
B4: KEY PERFORMANCE INDICATORS
B5: TOTAL REVENUE | E5: ORDERS | H5: UNITS SOLD | K5: AVG ORDER VALUE | N5: ACTIVE CUSTOMERS | Q5: REPEAT RATE
B6: =Analysis!$B$24 -> 229192.47 | E6: =Analysis!$B$25 -> 250 | H6: =Analysis!$B$26 -> 753 | K6: =Analysis!$B$27 -> 916.76988 | N6: =Analysis!$B$28 -> 50 | Q6: =Analysis!$B$30 -> 0.94
B7: =IF(H51>=0,"▲ ","▼ ")&TEXT(ABS(H51),"0.0%")&" vs target" -> ▼ 4.5% vs target | E7: =IF(H52>=0,"▲ ","▼ ")&TEXT(ABS(H52),"0.0%")&" vs target" -> ▼ 3.8% vs target | H7: =TEXT(Analysis!$B$26/Analysis!$B$25,"0.0")&" units per order" -> 3.0 units per order | K7: =IF(H53>=0,"▲ ","▼ ")&TEXT(ABS(H53),"0.0%")&" vs target" -> ▲ 1.9% vs target | N7: =Analysis!$B$29&" repeat buyers" -> 47 repeat buyers | Q7: =IF(H54>=0,"▲ ","▼ ")&TEXT(ABS(H54),"0.0%")&" vs target" -> ▼ 1.1% vs target
B9: INTERACTIVE FILTERS: choose from the dropdowns, the charts below update instantly
B10: REGION | E10: CATEGORY | H10: PAYMENT METHOD | K10: CUSTOMER SEGMENT | N10: FROM DATE | Q10: TO DATE
B11: All | E11: All | H11: All | K11: All | N11: 45383 | Q11: 45777
B13: SELECTED REVENUE | E13: SELECTED ORDERS | H13: SELECTED UNITS | K13: AVG ORDER | N13: SHARE OF TOTAL | Q13: VIEW
B14: =Calc!B70 -> 229192.47 | E14: =Calc!B71 -> 250 | H14: =Calc!B72 -> 753 | K14: =Calc!B73 -> 916.76988 | N14: =Calc!B74 -> 1 | Q14: =Calc!B75 -> Full dataset (no filters)
B16: TRENDS & MIX (respond to the filters above)
B17: Monthly Revenue Trend | K17: Revenue by Region
B33: Revenue by Category | H33: Top Products by Revenue | N33: Orders by Payment Method
B49: PERFORMANCE VS TARGET | TOP 10 CUSTOMERS
B50: KPI | D50: Actual | F50: Target | H50: Variance | I50: Status | K50: Rank | L50: Customer | O50: Total Spend | Q50: Share of revenue
B51: Total Revenue | D51: =Analysis!$B$24 -> 229192.47 | F51: 240000 | H51: =D51/F51-1 -> -0.045031375 | I51: =IF(H51>=0,"On target",IF(H51>=-0.1,"Watch","Behind")) -> Watch | K51: =Customers!L4 -> 1 | L51: =Customers!M4 -> Mark Carter | O51: =Customers!N4 -> 15659.65 | Q51: =Customers!O4 -> 0.068325325
B52: Orders | D52: =Analysis!$B$25 -> 250 | F52: 260 | H52: =D52/F52-1 -> -0.038461538 | I52: =IF(H52>=0,"On target",IF(H52>=-0.1,"Watch","Behind")) -> Watch | K52: =Customers!L5 -> 2 | L52: =Customers!M5 -> Edward Mitchell | O52: =Customers!N5 -> 11919.77 | Q52: =Customers!O5 -> 0.052007686
B53: Avg Order Value | D53: =Analysis!$B$27 -> 916.76988 | F53: 900 | H53: =D53/F53-1 -> 0.0186332 | I53: =IF(H53>=0,"On target",IF(H53>=-0.1,"Watch","Behind")) -> On target | K53: =Customers!L6 -> 3 | L53: =Customers!M6 -> Barbara Young | O53: =Customers!N6 -> 10649.8 | Q53: =Customers!O6 -> 0.046466623
B54: Repeat Rate | D54: =Analysis!$B$30 -> 0.94 | F54: 0.95 | H54: =D54/F54-1 -> -0.010526316 | I54: =IF(H54>=0,"On target",IF(H54>=-0.1,"Watch","Behind")) -> Watch | K54: =Customers!L7 -> 4 | L54: =Customers!M7 -> Patricia Moore | O54: =Customers!N7 -> 9799.73 | Q54: =Customers!O7 -> 0.042757644
B55: Last full-month revenue | D55: =Analysis!E101 -> 19899.38 | F55: =AVERAGE(Analysis!E90:E100) -> 18392.115 | H55: =D55/F55-1 -> 0.081951722 | I55: =IF(H55>=0,"On target",IF(H55>=-0.1,"Watch","Behind")) -> On target | K55: =Customers!L8 -> 5 | L55: =Customers!M8 -> Paul Baker | O55: =Customers!N8 -> 8309.74 | Q55: =Customers!O8 -> 0.036256601
B56: Yellow targets are editable assumptions, not dataset values. | K56: =Customers!L9 -> 6 | L56: =Customers!M9 -> Dorothy Nelson | O56: =Customers!N9 -> 8269.79 | Q56: =Customers!O9 -> 0.036082294
K57: =Customers!L10 -> 7 | L57: =Customers!M10 -> Karen Hill | O57: =Customers!N10 -> 8009.77 | Q57: =Customers!O10 -> 0.034947789
B58: Customer tiers | K58: =Customers!L11 -> 8 | L58: =Customers!M11 -> Daniel King | O58: =Customers!N11 -> 7309.8 | Q58: =Customers!O11 -> 0.031893718
B59: High-Value | D59: =COUNTIF(Customers!$G$4:$G$53,"High-Value") -> 10 | F59: =SUMIF(Customers!$G$4:$G$53,"High-Value",Customers!$C$4:$C$53) -> 93867.66 | H59: =F59/Analysis!$B$24 -> 0.40955822 | K59: =Customers!L12 -> 9 | L59: =Customers!M12 -> Lawrence Reed | O59: =Customers!N12 -> 6989.77 | Q59: =Customers!O12 -> 0.030497381
B60: Mid | D60: =COUNTIF(Customers!$G$4:$G$53,"Mid") -> 15 | F60: =SUMIF(Customers!$G$4:$G$53,"Mid",Customers!$C$4:$C$53) -> 82107.47 | H60: =F60/Analysis!$B$24 -> 0.3582468 | K60: =Customers!L13 -> 10 | L60: =Customers!M13 -> Joseph Jackson | O60: =Customers!N13 -> 6949.84 | Q60: =Customers!O13 -> 0.03032316
B61: Low | D61: =COUNTIF(Customers!$G$4:$G$53,"Low") -> 25 | F61: =SUMIF(Customers!$G$4:$G$53,"Low",Customers!$C$4:$C$53) -> 53217.34 | H61: =F61/Analysis!$B$24 -> 0.23219498
B62: PIVOT TABLES & PIVOT CHARTS: live PivotTables on the Raw Data table (use the ▼ report filters; right-click, Refresh after data changes)
B63: Revenue by Region | E63: Revenue by Category | H63: Orders by Payment | K63: Revenue by Month | N63: Revenue by Product
B64: Filter | E64: Filter | H64: Filter | K64: Filter | N64: Filter
B65: Category | C65: - all - | E65: Region | F65: - all - | H65: Region | I65: - all - | K65: Region | L65: - all - | N65: Region | O65: - all -
B66: Payment_Method | C66: - all - | E66: Payment_Method | F66: - all - | H66: Category | I66: - all - | K66: Category | L66: - all - | N66: Category | O66: - all -
B68: Region | C68: Revenue ($) | E68: Category | F68: Revenue ($) | H68: Payment_Method | I68: Orders | K68: Year_Month | L68: Revenue ($) | N68: Product_Name | O68: Revenue ($)
B69: Central | C69: 41288.34 | E69: Appliances | F69: 8338.74 | H69: Cash | I69: 76 | K69: 2024-04 | L69: 20919.33 | N69: Blender | O69: 5219.13
B70: East | C70: 59288.39 | E70: Electronics | F70: 171756.05 | H70: Credit Card | I70: 68 | K70: 2024-05 | L70: 17039.35 | N70: Bookshelf | O70: 15298.98
B71: North | C71: 50808.31 | E71: Furniture | F71: 49097.68 | H71: Debit Card | I71: 54 | K71: 2024-06 | L71: 19299.45 | N71: Coffee Maker | O71: 3119.61
B72: South | C72: 36398.75 | E72: Grand Total | F72: 229192.47 | H72: PayPal | I72: 52 | K72: 2024-07 | L72: 18479.4 | N72: Desk | O72: 23399.22
B73: West | C73: 41408.68 | H73: Grand Total | I73: 250 | K73: 2024-08 | L73: 15759.43 | N73: Headphones | O73: 7049.53
B74: Grand Total | C74: 229192.47 | K74: 2024-09 | L74: 12989.51 | N74: Keyboard | O74: 8009.11
K75: 2024-10 | L75: 20609.52 | N75: Laptop | O75: 67499.25
K76: 2024-11 | L76: 12309.44 | N76: Monitor | O76: 21999.12
K77: 2024-12 | L77: 23039.3 | N77: Office Chair | O77: 10399.48
K78: 2025-01 | L78: 25799.15 | N78: Smartphone | O78: 67199.04
K79: 2025-02 | L79: 16069.38 | N79: Grand Total | O79: 229192.47
K80: 2025-03 | L80: 19899.38
K81: 2025-04 | L81: 6979.83
K82: Grand Total | L82: 229192.47
B83: Pivot Chart: Revenue by Region (Bar) | H83: Pivot Chart: Monthly Revenue (Line) | N83: Pivot Chart: Category Mix (Pie)
B100: Pivot charts are linked to the PivotTable cell ranges above. Filters in the INTERACTIVE FILTERS band drive the top charts; the ▼ report filters inside each PivotTable drive the pivot band.

Sheet Report
B1: Final Report: Insights & Storytelling
B2: Every sentence below is formula-driven and updates with the data. Recommendations are suggestions to refine.
B4: 1. The big picture
B5: ="Total revenue is "&TEXT(Analysis!$B$24,"$#,##0")&" from "&Analysis!$B$25&" orders and "&Analysis!$B$26&" units across "&Analysis!$B$28&" customers, an average order value of "&TEXT(Analysis!$B$27,"$#,##0.00")&"." -> Total revenue is $2,29,192 from 250 orders and 753 units across 50 customers, an average order value of $916.77.
B7: 2. Who buys
B8: ="The top customer is "&Analysis!$B$51&". The top 5 customers generate "&TEXT(Analysis!$B$31,"0.0%")&" of revenue, and "&TEXT(Analysis!$B$30,"0%")&" of customers have bought more than once, so the base is loyal and revenue is not overly concentrated." -> The top customer is Mark Carter. The top 5 customers generate 24.6% of revenue, and 94% of customers have bought more than once, so the base is loyal and revenue is not overly concentrated.
B10: 3. What sells
B11: ="The most frequently purchased product is "&Analysis!$B$47&", but the highest-revenue product is "&Analysis!$B$49&" ("&TEXT(MAX(Analysis!E35:E44),"$#,##0")&"). Volume leaders and revenue leaders are different, so price point matters." -> The most frequently purchased product is Bookshelf, but the highest-revenue product is Laptop ($67,499). Volume leaders and revenue leaders are different, so price point matters.
B13: 4. Where
B14: ="The strongest region is "&Analysis!$B$62&" ("&TEXT(MAX(Analysis!C56:C60),"$#,##0")&") and the weakest is "&Analysis!$B$63&" ("&TEXT(MIN(Analysis!C56:C60),"$#,##0")&"), a gap of "&TEXT(MAX(Analysis!C56:C60)/MIN(Analysis!C56:C60)-1,"0%")&"." -> The strongest region is East ($59,288) and the weakest is South ($36,399), a gap of 63%.
B16: 5. When
B17: ="Best full month: "&INDEX(Analysis!B90:B101,MATCH(MAX(Analysis!E90:E101),Analysis!E90:E101,0))&" ("&TEXT(MAX(Analysis!E90:E101),"$#,##0")&"); weakest: "&INDEX(Analysis!B90:B101,MATCH(MIN(Analysis!E90:E101),Analysis!E90:E101,0))&" ("&TEXT(MIN(Analysis!E90:E101),"$#,##0")&")." -> Best full month: Jan-25 ($25,799); weakest: Nov-24 ($12,309).
B19: 6. Trend (regression)
B20: ="Linear regression shows revenue changing by "&TEXT(Analysis!$B$107,"$#,##0")&" per month (R-squared "&TEXT(Analysis!$B$109,"0.00")&", p-value "&TEXT(Analysis!$B$113,"0.000")&"). "&Analysis!$B$115&". Forecast for the next month: "&TEXT(Analysis!$B$114,"$#,##0")&"." -> Linear regression shows revenue changing by $160 per month (R-squared 0.02, p-value 0.651). Trend is NOT statistically significant (p >= 0.05). Forecast for the next month: $19,554.
B22: 7. How customers pay
B23: ="The most used payment method is "&Analysis!$B$79&"." -> The most used payment method is Cash.
B25: 8. Cross-sell opportunity
B26: ="Of the top 15 spenders, "&Customers!$S$55&" also bought a Laptop. The rest are cross-sell targets for the highest-ticket product." -> Of the top 15 spenders, 12 also bought a Laptop. The rest are cross-sell targets for the highest-ticket product.
B28: 9. What-if
B29: ="Optimistic scenario (+5% price, +10% volume) projects "&TEXT(Analysis!$D$124,"$#,##0")&"; pessimistic (-3% price, -8% volume, 5% discount) projects "&TEXT(Analysis!$E$124,"$#,##0")&". Goal Seek: with the current volume and discount inputs, a price change of "&TEXT(Analysis!$B$129,"0.0%")&" is needed to reach the "&TEXT(Analysis!B127,"0%")&" revenue uplift target." -> Optimistic scenario (+5% price, +10% volume) projects $2,64,717; pessimistic (-3% price, -8% volume, 5% discount) projects $1,94,305. Goal Seek: with the current volume and discount inputs, a price change of 20.0% is needed to reach the 20% revenue uplift target.
B31: 10. Data-quality note
B32: Each Customer_ID appears with several different Regions, Segments and Customer_Since dates (up to 5 regions for one customer). These behave as per-transaction fields, so customer analysis groups by Customer_ID and regional analysis uses the transaction Region. Recommend fixing the source system.
B34: 11. Recommendations
B35: ="(1) Run a laptop/smartphone upsell campaign for high-value customers. (2) Grow "&Analysis!$B$63&" with targeted promotions. (3) Keep "&Analysis!$B$47&" well stocked as the volume driver. (4) Review the revenue trend monthly using the dashboard." -> (1) Run a laptop/smartphone upsell campaign for high-value customers. (2) Grow South with targeted promotions. (3) Keep Bookshelf well stocked as the volume driver. (4) Review the revenue trend monthly using the dashboard.

Sheet Raw Data
A1: Transaction_ID | B1: Date | C1: Customer_ID | D1: Customer_Name | E1: Product_ID | F1: Product_Name | G1: Category | H1: Quantity | I1: Unit_Price | J1: Payment_Method | K1: Region | L1: Customer_Segment | M1: Customer_Since | N1: Total_Amount | O1: Check | P1: Month_End | Q1: Month_Label | R1: Tenure_Years | S1: Tenure_Months | T1: Days_Since_Sale | U1: Initials | V1: Product_Code | W1: Order_Code | X1: Repeat_Flag | Y1: Filter_Seq | Z1: Year_Month
A2: TRX0155 | B2: 45393 | C2: CUST023 | D2: Paul Baker | E2: P009 | F2: Monitor | G2: Electronics | H2: 3 | I2: 249.99 | J2: Cash | K2: Central | L2: Basic | M2: 44425 | N2: 749.97 | O2: =IF(ROUND(H2*I2-N2,2)=0,"OK","Error") -> OK | P2: =EOMONTH(B2,0) -> 45412 | Q2: =TEXT(B2,"mmm-yy") -> Apr-24 | R2: =DATEDIF(M2,B2,"Y") -> 2 | S2: =DATEDIF(M2,B2,"M") -> 31 | T2: =TODAY()-B2 -> 925 | U2: =LEFT(D2,1)&MID(D2,FIND(" ",D2)+1,1) -> PB | V2: =UPPER(LEFT(F2,3)) -> MON | W2: =UPPER(LEFT(K2,1))&"-"&TEXT(B2,"yymm")&"-"&RIGHT(A2,3) -> C-2404-155 | X2: =IF(COUNTIF($D$2:D2,D2)>1,"Repeat","First") -> First | Y2: =IF(AND(K2=Filter!$B$4,N2>=Filter!$B$5),MAX(Y$1:Y1)+1,"") | Z2: =TEXT(B2,"yyyy-mm") -> 2024-04
A3: TRX0023 | B3: 45396 | C3: CUST013 | D3: Joseph Jackson | E3: P009 | F3: Monitor | G3: Electronics | H3: 3 | I3: 249.99 | J3: Credit Card | K3: Central | L3: Premium | M3: 44575 | N3: 749.97 | O3: =IF(ROUND(H3*I3-N3,2)=0,"OK","Error") -> OK | P3: =EOMONTH(B3,0) -> 45412 | Q3: =TEXT(B3,"mmm-yy") -> Apr-24 | R3: =DATEDIF(M3,B3,"Y") -> 2 | S3: =DATEDIF(M3,B3,"M") -> 27 | T3: =TODAY()-B3 -> 922 | U3: =LEFT(D3,1)&MID(D3,FIND(" ",D3)+1,1) -> JJ | V3: =UPPER(LEFT(F3,3)) -> MON | W3: =UPPER(LEFT(K3,1))&"-"&TEXT(B3,"yymm")&"-"&RIGHT(A3,3) -> C-2404-023 | X3: =IF(COUNTIF($D$2:D3,D3)>1,"Repeat","First") -> First | Y3: =IF(AND(K3=Filter!$B$4,N3>=Filter!$B$5),MAX(Y$1:Y2)+1,"") | Z3: =TEXT(B3,"yyyy-mm") -> 2024-04
A4: TRX0139 | B4: 45399 | C4: CUST021 | D4: Kevin Scott | E4: P005 | F4: Blender | G4: Appliances | H4: 3 | I4: 59.99 | J4: PayPal | K4: South | L4: Standard | M4: 45262 | N4: 179.97 | O4: =IF(ROUND(H4*I4-N4,2)=0,"OK","Error") -> OK | P4: =EOMONTH(B4,0) -> 45412 | Q4: =TEXT(B4,"mmm-yy") -> Apr-24 | R4: =DATEDIF(M4,B4,"Y") -> 0 | S4: =DATEDIF(M4,B4,"M") -> 4 | T4: =TODAY()-B4 -> 919 | U4: =LEFT(D4,1)&MID(D4,FIND(" ",D4)+1,1) -> KS | V4: =UPPER(LEFT(F4,3)) -> BLE | W4: =UPPER(LEFT(K4,1))&"-"&TEXT(B4,"yymm")&"-"&RIGHT(A4,3) -> S-2404-139 | X4: =IF(COUNTIF($D$2:D4,D4)>1,"Repeat","First") -> First | Y4: =IF(AND(K4=Filter!$B$4,N4>=Filter!$B$5),MAX(Y$1:Y3)+1,"") | Z4: =TEXT(B4,"yyyy-mm") -> 2024-04
A5: TRX0043 | B5: 45400 | C5: CUST046 | D5: Kathleen Bennett | E5: P005 | F5: Blender | G5: Appliances | H5: 3 | I5: 59.99 | J5: Cash | K5: North | L5: Premium | M5: 45114 | N5: 179.97 | O5: =IF(ROUND(H5*I5-N5,2)=0,"OK","Error") -> OK | P5: =EOMONTH(B5,0) -> 45412 | Q5: =TEXT(B5,"mmm-yy") -> Apr-24 | R5: =DATEDIF(M5,B5,"Y") -> 0 | S5: =DATEDIF(M5,B5,"M") -> 9 | T5: =TODAY()-B5 -> 918 | U5: =LEFT(D5,1)&MID(D5,FIND(" ",D5)+1,1) -> KB | V5: =UPPER(LEFT(F5,3)) -> BLE | W5: =UPPER(LEFT(K5,1))&"-"&TEXT(B5,"yymm")&"-"&RIGHT(A5,3) -> N-2404-043 | X5: =IF(COUNTIF($D$2:D5,D5)>1,"Repeat","First") -> First | Y5: =IF(AND(K5=Filter!$B$4,N5>=Filter!$B$5),MAX(Y$1:Y4)+1,"") | Z5: =TEXT(B5,"yyyy-mm") -> 2024-04
A6: TRX0212 | B6: 45400 | C6: CUST003 | D6: Michael Brown | E6: P008 | F6: Bookshelf | G6: Furniture | H6: 5 | I6: 149.99 | J6: Credit Card | K6: North | L6: Premium | M6: 45295 | N6: 749.95 | O6: =IF(ROUND(H6*I6-N6,2)=0,"OK","Error") -> OK | P6: =EOMONTH(B6,0) -> 45412 | Q6: =TEXT(B6,"mmm-yy") -> Apr-24 | R6: =DATEDIF(M6,B6,"Y") -> 0 | S6: =DATEDIF(M6,B6,"M") -> 3 | T6: =TODAY()-B6 -> 918 | U6: =LEFT(D6,1)&MID(D6,FIND(" ",D6)+1,1) -> MB | V6: =UPPER(LEFT(F6,3)) -> BOO | W6: =UPPER(LEFT(K6,1))&"-"&TEXT(B6,"yymm")&"-"&RIGHT(A6,3) -> N-2404-212 | X6: =IF(COUNTIF($D$2:D6,D6)>1,"Repeat","First") -> First | Y6: =IF(AND(K6=Filter!$B$4,N6>=Filter!$B$5),MAX(Y$1:Y5)+1,"") | Z6: =TEXT(B6,"yyyy-mm") -> 2024-04
A7: TRX0092 | B7: 45403 | C7: CUST024 | D7: Dorothy Nelson | E7: P005 | F7: Blender | G7: Appliances | H7: 2 | I7: 59.99 | J7: Cash | K7: West | L7: Standard | M7: 44746 | N7: 119.98 | O7: =IF(ROUND(H7*I7-N7,2)=0,"OK","Error") -> OK | P7: =EOMONTH(B7,0) -> 45412 | Q7: =TEXT(B7,"mmm-yy") -> Apr-24 | R7: =DATEDIF(M7,B7,"Y") -> 1 | S7: =DATEDIF(M7,B7,"M") -> 21 | T7: =TODAY()-B7 -> 915 | U7: =LEFT(D7,1)&MID(D7,FIND(" ",D7)+1,1) -> DN | V7: =UPPER(LEFT(F7,3)) -> BLE | W7: =UPPER(LEFT(K7,1))&"-"&TEXT(B7,"yymm")&"-"&RIGHT(A7,3) -> W-2404-092 | X7: =IF(COUNTIF($D$2:D7,D7)>1,"Repeat","First") -> First | Y7: =IF(AND(K7=Filter!$B$4,N7>=Filter!$B$5),MAX(Y$1:Y6)+1,"") | Z7: =TEXT(B7,"yyyy-mm") -> 2024-04
A8: TRX0193 | B8: 45403 | C8: CUST024 | D8: Dorothy Nelson | E8: P003 | F8: Headphones | G8: Electronics | H8: 5 | I8: 149.99 | J8: Credit Card | K8: Central | L8: Standard | M8: 44418 | N8: 749.95 | O8: =IF(ROUND(H8*I8-N8,2)=0,"OK","Error") -> OK | P8: =EOMONTH(B8,0) -> 45412 | Q8: =TEXT(B8,"mmm-yy") -> Apr-24 | R8: =DATEDIF(M8,B8,"Y") -> 2 | S8: =DATEDIF(M8,B8,"M") -> 32 | T8: =TODAY()-B8 -> 915 | U8: =LEFT(D8,1)&MID(D8,FIND(" ",D8)+1,1) -> DN | V8: =UPPER(LEFT(F8,3)) -> HEA | W8: =UPPER(LEFT(K8,1))&"-"&TEXT(B8,"yymm")&"-"&RIGHT(A8,3) -> C-2404-193 | X8: =IF(COUNTIF($D$2:D8,D8)>1,"Repeat","First") -> Repeat | Y8: =IF(AND(K8=Filter!$B$4,N8>=Filter!$B$5),MAX(Y$1:Y7)+1,"") | Z8: =TEXT(B8,"yyyy-mm") -> 2024-04
A9: TRX0240 | B9: 45403 | C9: CUST017 | D9: Charles Allen | E9: P005 | F9: Blender | G9: Appliances | H9: 3 | I9: 59.99 | J9: Debit Card | K9: South | L9: Basic | M9: 45007 | N9: 179.97 | O9: =IF(ROUND(H9*I9-N9,2)=0,"OK","Error") -> OK | P9: =EOMONTH(B9,0) -> 45412 | Q9: =TEXT(B9,"mmm-yy") -> Apr-24 | R9: =DATEDIF(M9,B9,"Y") -> 1 | S9: =DATEDIF(M9,B9,"M") -> 12 | T9: =TODAY()-B9 -> 915 | U9: =LEFT(D9,1)&MID(D9,FIND(" ",D9)+1,1) -> CA | V9: =UPPER(LEFT(F9,3)) -> BLE | W9: =UPPER(LEFT(K9,1))&"-"&TEXT(B9,"yymm")&"-"&RIGHT(A9,3) -> S-2404-240 | X9: =IF(COUNTIF($D$2:D9,D9)>1,"Repeat","First") -> First | Y9: =IF(AND(K9=Filter!$B$4,N9>=Filter!$B$5),MAX(Y$1:Y8)+1,"") | Z9: =TEXT(B9,"yyyy-mm") -> 2024-04
A10: TRX0135 | B10: 45405 | C10: CUST009 | D10: Robert Thomas | E10: P001 | F10: Laptop | G10: Electronics | H10: 3 | I10: 899.99 | J10: PayPal | K10: East | L10: Standard | M10: 45299 | N10: 2699.97 | O10: =IF(ROUND(H10*I10-N10,2)=0,"OK","Error") -> OK | P10: =EOMONTH(B10,0) -> 45412 | Q10: =TEXT(B10,"mmm-yy") -> Apr-24 | R10: =DATEDIF(M10,B10,"Y") -> 0 | S10: =DATEDIF(M10,B10,"M") -> 3 | T10: =TODAY()-B10 -> 913 | U10: =LEFT(D10,1)&MID(D10,FIND(" ",D10)+1,1) -> RT | V10: =UPPER(LEFT(F10,3)) -> LAP | W10: =UPPER(LEFT(K10,1))&"-"&TEXT(B10,"yymm")&"-"&RIGHT(A10,3) -> E-2404-135 | X10: =IF(COUNTIF($D$2:D10,D10)>1,"Repeat","First") -> First | Y10: =IF(AND(K10=Filter!$B$4,N10>=Filter!$B$5),MAX(Y$1:Y9)+1,"") | Z10: =TEXT(B10,"yyyy-mm") -> 2024-04
A11: TRX0185 | B11: 45408 | C11: CUST026 | D11: Karen Hill | E11: P005 | F11: Blender | G11: Appliances | H11: 3 | I11: 59.99 | J11: Cash | K11: West | L11: Premium | M11: 45207 | N11: 179.97 | O11: =IF(ROUND(H11*I11-N11,2)=0,"OK","Error") -> OK | P11: =EOMONTH(B11,0) -> 45412 | Q11: =TEXT(B11,"mmm-yy") -> Apr-24 | R11: =DATEDIF(M11,B11,"Y") -> 0 | S11: =DATEDIF(M11,B11,"M") -> 6 | T11: =TODAY()-B11 -> 910 | U11: =LEFT(D11,1)&MID(D11,FIND(" ",D11)+1,1) -> KH | V11: =UPPER(LEFT(F11,3)) -> BLE | W11: =UPPER(LEFT(K11,1))&"-"&TEXT(B11,"yymm")&"-"&RIGHT(A11,3) -> W-2404-185 | X11: =IF(COUNTIF($D$2:D11,D11)>1,"Repeat","First") -> First | Y11: =IF(AND(K11=Filter!$B$4,N11>=Filter!$B$5),MAX(Y$1:Y10)+1,"") | Z11: =TEXT(B11,"yyyy-mm") -> 2024-04
A12: TRX0138 | B12: 45408 | C12: CUST022 | D12: Susan Green | E12: P008 | F12: Bookshelf | G12: Furniture | H12: 1 | I12: 149.99 | J12: Credit Card | K12: West | L12: Standard | M12: 45103 | N12: 149.99 | O12: =IF(ROUND(H12*I12-N12,2)=0,"OK","Error") -> OK | P12: =EOMONTH(B12,0) -> 45412 | Q12: =TEXT(B12,"mmm-yy") -> Apr-24 | R12: =DATEDIF(M12,B12,"Y") -> 0 | S12: =DATEDIF(M12,B12,"M") -> 10 | T12: =TODAY()-B12 -> 910 | U12: =LEFT(D12,1)&MID(D12,FIND(" ",D12)+1,1) -> SG | V12: =UPPER(LEFT(F12,3)) -> BOO | W12: =UPPER(LEFT(K12,1))&"-"&TEXT(B12,"yymm")&"-"&RIGHT(A12,3) -> W-2404-138 | X12: =IF(COUNTIF($D$2:D12,D12)>1,"Repeat","First") -> First | Y12: =IF(AND(K12=Filter!$B$4,N12>=Filter!$B$5),MAX(Y$1:Y11)+1,"") | Z12: =TEXT(B12,"yyyy-mm") -> 2024-04
A13: TRX0209 | B13: 45408 | C13: CUST046 | D13: Kathleen Bennett | E13: P008 | F13: Bookshelf | G13: Furniture | H13: 5 | I13: 149.99 | J13: Debit Card | K13: North | L13: Basic | M13: 44830 | N13: 749.95 | O13: =IF(ROUND(H13*I13-N13,2)=0,"OK","Error") -> OK | P13: =EOMONTH(B13,0) -> 45412 | Q13: =TEXT(B13,"mmm-yy") -> Apr-24 | R13: =DATEDIF(M13,B13,"Y") -> 1 | S13: =DATEDIF(M13,B13,"M") -> 19 | T13: =TODAY()-B13 -> 910 | U13: =LEFT(D13,1)&MID(D13,FIND(" ",D13)+1,1) -> KB | V13: =UPPER(LEFT(F13,3)) -> BOO | W13: =UPPER(LEFT(K13,1))&"-"&TEXT(B13,"yymm")&"-"&RIGHT(A13,3) -> N-2404-209 | X13: =IF(COUNTIF($D$2:D13,D13)>1,"Repeat","First") -> Repeat | Y13: =IF(AND(K13=Filter!$B$4,N13>=Filter!$B$5),MAX(Y$1:Y12)+1,"") | Z13: =TEXT(B13,"yyyy-mm") -> 2024-04
... A251: TRX0064 | B251: 45758 | C251: CUST031 | D251: Steven Turner | E251: P010 | F251: Keyboard | G251: Electronics | H251: 3 | I251: 89.99 | J251: Debit Card | K251: North | L251: Premium | M251: 44878 | N251: 269.97 | O251: =IF(ROUND(H251*I251-N251,2)=0,"OK","Error") -> OK | P251: =EOMONTH(B251,0) -> 45777 | Q251: =TEXT(B251,"mmm-yy") -> Apr-25 | R251: =DATEDIF(M251,B251,"Y") -> 2 | S251: =DATEDIF(M251,B251,"M") -> 28 | T251: =TODAY()-B251 -> 560 | U251: =LEFT(D251,1)&MID(D251,FIND(" ",D251)+1,1) -> ST | V251: =UPPER(LEFT(F251,3)) -> KEY | W251: =UPPER(LEFT(K251,1))&"-"&TEXT(B251,"yymm")&"-"&RIGHT(A251,3) -> N-2504-064 | X251: =IF(COUNTIF($D$2:D251,D251)>1,"Repeat","First") -> Repeat | Y251: =IF(AND(K251=Filter!$B$4,N251>=Filter!$B$5),MAX(Y$1:Y250)+1,"") | Z251: =TEXT(B251,"yyyy-mm") -> 2025-04

Sheet Analysis
A1: Analysis
A3: 1. Date & Time Functions (TODAY, NOW, DATEDIF, EOMONTH)
A4: Today | B4: =TODAY() -> 46318
A5: Now (date & time) | B5: =NOW() -> 46318.648
A6: End of current month | B6: =EOMONTH(TODAY(),0) -> 46326
A7: Start of current month | B7: =EOMONTH(TODAY(),-1)+1 -> 46296
A8: First transaction | B8: =MIN('Raw Data'!$B$2:$B$251) -> 45393
A9: Last transaction | B9: =MAX('Raw Data'!$B$2:$B$251) -> 45758
A10: Dataset span (months, DATEDIF) | B10: =DATEDIF(B8,B9,"M") -> 12
A11: Days since last transaction | B11: =TODAY()-B9 -> 560
A12: Avg customer tenure at purchase (years) | B12: =AVERAGE('Raw Data'!$S$2:$S$251)/12 -> 1.9093333
A14: 2. Timestamp with NOW() + Iterative Calculation (circular on purpose; File > Options > Formulas > Enable iterative calculation)
A15: Entry (type here) | B15: Timestamp (freezes once entry is typed)
A16: Order 1001 | B16: =IF(A16="","",IF(OR(B16="",B16=0),NOW(),B16)) -> 46318.409
A17: Order 1002 | B17: =IF(A17="","",IF(OR(B17="",B17=0),NOW(),B17)) -> 46318.409
A18: Order 1003 | B18: =IF(A18="","",IF(OR(B18="",B18=0),NOW(),B18)) -> 46318.409
B19: =IF(A19="","",IF(OR(B19="",B19=0),NOW(),B19))
B20: =IF(A20="","",IF(OR(B20="",B20=0),NOW(),B20))
A21: Type anything in A19 or A20 and the timestamp appears and stays fixed.
A23: 3. Headline KPIs
A24: Total Revenue | B24: =SUM('Raw Data'!$N$2:$N$251) -> 229192.47
A25: Total Orders | B25: =COUNTA('Raw Data'!$A$2:$A$251) -> 250
A26: Units Sold | B26: =SUM('Raw Data'!$H$2:$H$251) -> 753
A27: Avg Order Value | B27: =B24/B25 -> 916.76988
A28: Active Customers | B28: =COUNTA(Customers!A4:A53) -> 50
A29: Repeat Customers (2+ orders) | B29: =COUNTIF(Customers!J4:J53,"Repeat") -> 47
A30: Repeat Rate | B30: =B29/B28 -> 0.94
A31: Top-5 customers: share of revenue | B31: =SUMIF(Customers!F4:F53,"<=5",Customers!C4:C53)/B24 -> 0.24581388
A33: 4. Products (most frequently purchased, units, revenue)
A34: Product_ID | B34: Product_Name | C34: Orders | D34: Units | E34: Revenue | F34: Share | G34: Rev_Rank
A35: P001 | B35: =INDEX('Raw Data'!$F$2:$F$251,MATCH(A35,'Raw Data'!$E$2:$E$251,0)) -> Laptop | C35: =COUNTIF('Raw Data'!$E$2:$E$251,A35) -> 24 | D35: =SUMIFS('Raw Data'!$H$2:$H$251,'Raw Data'!$E$2:$E$251,A35) -> 75 | E35: =SUMIFS('Raw Data'!$N$2:$N$251,'Raw Data'!$E$2:$E$251,A35) -> 67499.25 | F35: =E35/$B$24 -> 0.29450902 | G35: =RANK(E35,$E$35:$E$44,0) -> 1
A36: P002 | B36: =INDEX('Raw Data'!$F$2:$F$251,MATCH(A36,'Raw Data'!$E$2:$E$251,0)) -> Smartphone | C36: =COUNTIF('Raw Data'!$E$2:$E$251,A36) -> 31 | D36: =SUMIFS('Raw Data'!$H$2:$H$251,'Raw Data'!$E$2:$E$251,A36) -> 96 | E36: =SUMIFS('Raw Data'!$N$2:$N$251,'Raw Data'!$E$2:$E$251,A36) -> 67199.04 | F36: =E36/$B$24 -> 0.29319916 | G36: =RANK(E36,$E$35:$E$44,0) -> 2
A37: P003 | B37: =INDEX('Raw Data'!$F$2:$F$251,MATCH(A37,'Raw Data'!$E$2:$E$251,0)) -> Headphones | C37: =COUNTIF('Raw Data'!$E$2:$E$251,A37) -> 16 | D37: =SUMIFS('Raw Data'!$H$2:$H$251,'Raw Data'!$E$2:$E$251,A37) -> 47 | E37: =SUMIFS('Raw Data'!$N$2:$N$251,'Raw Data'!$E$2:$E$251,A37) -> 7049.53 | F37: =E37/$B$24 -> 0.030758122 | G37: =RANK(E37,$E$35:$E$44,0) -> 8
A38: P004 | B38: =INDEX('Raw Data'!$F$2:$F$251,MATCH(A38,'Raw Data'!$E$2:$E$251,0)) -> Coffee Maker | C38: =COUNTIF('Raw Data'!$E$2:$E$251,A38) -> 14 | D38: =SUMIFS('Raw Data'!$H$2:$H$251,'Raw Data'!$E$2:$E$251,A38) -> 39 | E38: =SUMIFS('Raw Data'!$N$2:$N$251,'Raw Data'!$E$2:$E$251,A38) -> 3119.61 | F38: =E38/$B$24 -> 0.013611311 | G38: =RANK(E38,$E$35:$E$44,0) -> 10
A39: P005 | B39: =INDEX('Raw Data'!$F$2:$F$251,MATCH(A39,'Raw Data'!$E$2:$E$251,0)) -> Blender | C39: =COUNTIF('Raw Data'!$E$2:$E$251,A39) -> 29 | D39: =SUMIFS('Raw Data'!$H$2:$H$251,'Raw Data'!$E$2:$E$251,A39) -> 87 | E39: =SUMIFS('Raw Data'!$N$2:$N$251,'Raw Data'!$E$2:$E$251,A39) -> 5219.13 | F39: =E39/$B$24 -> 0.022771821 | G39: =RANK(E39,$E$35:$E$44,0) -> 9
A40: P006 | B40: =INDEX('Raw Data'!$F$2:$F$251,MATCH(A40,'Raw Data'!$E$2:$E$251,0)) -> Office Chair | C40: =COUNTIF('Raw Data'!$E$2:$E$251,A40) -> 15 | D40: =SUMIFS('Raw Data'!$H$2:$H$251,'Raw Data'!$E$2:$E$251,A40) -> 52 | E40: =SUMIFS('Raw Data'!$N$2:$N$251,'Raw Data'!$E$2:$E$251,A40) -> 10399.48 | F40: =E40/$B$24 -> 0.04537444 | G40: =RANK(E40,$E$35:$E$44,0) -> 6
A41: P007 | B41: =INDEX('Raw Data'!$F$2:$F$251,MATCH(A41,'Raw Data'!$E$2:$E$251,0)) -> Desk | C41: =COUNTIF('Raw Data'!$E$2:$E$251,A41) -> 26 | D41: =SUMIFS('Raw Data'!$H$2:$H$251,'Raw Data'!$E$2:$E$251,A41) -> 78 | E41: =SUMIFS('Raw Data'!$N$2:$N$251,'Raw Data'!$E$2:$E$251,A41) -> 23399.22 | F41: =E41/$B$24 -> 0.10209419 | G41: =RANK(E41,$E$35:$E$44,0) -> 3
A42: P008 | B42: =INDEX('Raw Data'!$F$2:$F$251,MATCH(A42,'Raw Data'!$E$2:$E$251,0)) -> Bookshelf | C42: =COUNTIF('Raw Data'!$E$2:$E$251,A42) -> 35 | D42: =SUMIFS('Raw Data'!$H$2:$H$251,'Raw Data'!$E$2:$E$251,A42) -> 102 | E42: =SUMIFS('Raw Data'!$N$2:$N$251,'Raw Data'!$E$2:$E$251,A42) -> 15298.98 | F42: =E42/$B$24 -> 0.066751669 | G42: =RANK(E42,$E$35:$E$44,0) -> 5
A43: P009 | B43: =INDEX('Raw Data'!$F$2:$F$251,MATCH(A43,'Raw Data'!$E$2:$E$251,0)) -> Monitor | C43: =COUNTIF('Raw Data'!$E$2:$E$251,A43) -> 26 | D43: =SUMIFS('Raw Data'!$H$2:$H$251,'Raw Data'!$E$2:$E$251,A43) -> 88 | E43: =SUMIFS('Raw Data'!$N$2:$N$251,'Raw Data'!$E$2:$E$251,A43) -> 21999.12 | F43: =E43/$B$24 -> 0.095985352 | G43: =RANK(E43,$E$35:$E$44,0) -> 4
A44: P010 | B44: =INDEX('Raw Data'!$F$2:$F$251,MATCH(A44,'Raw Data'!$E$2:$E$251,0)) -> Keyboard | C44: =COUNTIF('Raw Data'!$E$2:$E$251,A44) -> 34 | D44: =SUMIFS('Raw Data'!$H$2:$H$251,'Raw Data'!$E$2:$E$251,A44) -> 89 | E44: =SUMIFS('Raw Data'!$N$2:$N$251,'Raw Data'!$E$2:$E$251,A44) -> 8009.11 | F44: =E44/$B$24 -> 0.034944909 | G44: =RANK(E44,$E$35:$E$44,0) -> 7
A45: Total | C45: =SUM(C35:C44) -> 250 | D45: =SUM(D35:D44) -> 753 | E45: =SUM(E35:E44) -> 229192.47 | F45: =SUM(F35:F44) -> 1
A47: Most frequently purchased product (by orders) | B47: =INDEX(B35:B44,MATCH(MAX(C35:C44),C35:C44,0)) -> Bookshelf
A48: Most units sold | B48: =INDEX(B35:B44,MATCH(MAX(D35:D44),D35:D44,0)) -> Bookshelf
A49: Highest-revenue product | B49: =INDEX(B35:B44,MATCH(MAX(E35:E44),E35:E44,0)) -> Laptop
A50: Most frequent buyer (by orders) | B50: =INDEX(Customers!B4:B53,MATCH(MAX(Customers!D4:D53),Customers!D4:D53,0)) -> Mark Carter
A51: Top customer by spend | B51: =INDEX(Customers!B4:B53,MATCH(1,Customers!F4:F53,0)) -> Mark Carter
A54: 5. Regional Sales
A55: Region | B55: Orders | C55: Revenue | D55: Share | E55: Avg_Order | F55: Rev_Rank
A56: Central | B56: =COUNTIF('Raw Data'!$K$2:$K$251,A56) -> 54 | C56: =SUMIFS('Raw Data'!$N$2:$N$251,'Raw Data'!$K$2:$K$251,A56) -> 41288.34 | D56: =C56/$B$24 -> 0.18014702 | E56: =IF(B56=0,0,C56/B56) -> 764.59889 | F56: =RANK(C56,$C$56:$C$60,0) -> 4
A57: East | B57: =COUNTIF('Raw Data'!$K$2:$K$251,A57) -> 48 | C57: =SUMIFS('Raw Data'!$N$2:$N$251,'Raw Data'!$K$2:$K$251,A57) -> 59288.39 | D57: =C57/$B$24 -> 0.25868385 | E57: =IF(B57=0,0,C57/B57) -> 1235.1748 | F57: =RANK(C57,$C$56:$C$60,0) -> 1
A58: North | B58: =COUNTIF('Raw Data'!$K$2:$K$251,A58) -> 59 | C58: =SUMIFS('Raw Data'!$N$2:$N$251,'Raw Data'!$K$2:$K$251,A58) -> 50808.31 | D58: =C58/$B$24 -> 0.22168403 | E58: =IF(B58=0,0,C58/B58) -> 861.1578 | F58: =RANK(C58,$C$56:$C$60,0) -> 2
A59: South | B59: =COUNTIF('Raw Data'!$K$2:$K$251,A59) -> 42 | C59: =SUMIFS('Raw Data'!$N$2:$N$251,'Raw Data'!$K$2:$K$251,A59) -> 36398.75 | D59: =C59/$B$24 -> 0.15881303 | E59: =IF(B59=0,0,C59/B59) -> 866.6369 | F59: =RANK(C59,$C$56:$C$60,0) -> 5
A60: West | B60: =COUNTIF('Raw Data'!$K$2:$K$251,A60) -> 47 | C60: =SUMIFS('Raw Data'!$N$2:$N$251,'Raw Data'!$K$2:$K$251,A60) -> 41408.68 | D60: =C60/$B$24 -> 0.18067208 | E60: =IF(B60=0,0,C60/B60) -> 881.03574 | F60: =RANK(C60,$C$56:$C$60,0) -> 3
A61: Total | B61: =SUM(B56:B60) -> 250 | C61: =SUM(C56:C60) -> 229192.47 | D61: =SUM(D56:D60) -> 1
A62: Top region | B62: =INDEX(A56:A60,MATCH(MAX(C56:C60),C56:C60,0)) -> East
A63: Weakest region | B63: =INDEX(A56:A60,MATCH(MIN(C56:C60),C56:C60,0)) -> South
A65: 6. Category Sales
A66: Category | B66: Orders | C66: Revenue | D66: Share | E66: Avg_Order | F66: Rev_Rank
A67: Appliances | B67: =COUNTIF('Raw Data'!$G$2:$G$251,A67) -> 43 | C67: =SUMIFS('Raw Data'!$N$2:$N$251,'Raw Data'!$G$2:$G$251,A67) -> 8338.74 | D67: =C67/$B$24 -> 0.036383132 | E67: =IF(B67=0,0,C67/B67) -> 193.92419 | F67: =RANK(C67,$C$67:$C$69,0) -> 3
A68: Electronics | B68: =COUNTIF('Raw Data'!$G$2:$G$251,A68) -> 131 | C68: =SUMIFS('Raw Data'!$N$2:$N$251,'Raw Data'!$G$2:$G$251,A68) -> 171756.05 | D68: =C68/$B$24 -> 0.74939657 | E68: =IF(B68=0,0,C68/B68) -> 1311.1149 | F68: =RANK(C68,$C$67:$C$69,0) -> 1
A69: Furniture | B69: =COUNTIF('Raw Data'!$G$2:$G$251,A69) -> 76 | C69: =SUMIFS('Raw Data'!$N$2:$N$251,'Raw Data'!$G$2:$G$251,A69) -> 49097.68 | D69: =C69/$B$24 -> 0.2142203 | E69: =IF(B69=0,0,C69/B69) -> 646.02211 | F69: =RANK(C69,$C$67:$C$69,0) -> 2
A70: Total | B70: =SUM(B67:B69) -> 250 | C70: =SUM(C67:C69) -> 229192.47 | D70: =SUM(D67:D69) -> 1
A72: 7. Payment Methods
A73: Payment_Method | B73: Orders | C73: Revenue | D73: Share | E73: Avg_Order | F73: Rev_Rank
A74: Cash | B74: =COUNTIF('Raw Data'!$J$2:$J$251,A74) -> 76 | C74: =SUMIFS('Raw Data'!$N$2:$N$251,'Raw Data'!$J$2:$J$251,A74) -> 57427.79 | D74: =C74/$B$24 -> 0.25056578 | E74: =IF(B74=0,0,C74/B74) -> 755.62882 | F74: =RANK(C74,$C$74:$C$77,0) -> 3
A75: Credit Card | B75: =COUNTIF('Raw Data'!$J$2:$J$251,A75) -> 68 | C75: =SUMIFS('Raw Data'!$N$2:$N$251,'Raw Data'!$J$2:$J$251,A75) -> 61447.96 | D75: =C75/$B$24 -> 0.26810636 | E75: =IF(B75=0,0,C75/B75) -> 903.64647 | F75: =RANK(C75,$C$74:$C$77,0) -> 1
A76: Debit Card | B76: =COUNTIF('Raw Data'!$J$2:$J$251,A76) -> 54 | C76: =SUMIFS('Raw Data'!$N$2:$N$251,'Raw Data'!$J$2:$J$251,A76) -> 52118.31 | D76: =C76/$B$24 -> 0.22739975 | E76: =IF(B76=0,0,C76/B76) -> 965.15389 | F76: =RANK(C76,$C$74:$C$77,0) -> 4
A77: PayPal | B77: =COUNTIF('Raw Data'!$J$2:$J$251,A77) -> 52 | C77: =SUMIFS('Raw Data'!$N$2:$N$251,'Raw Data'!$J$2:$J$251,A77) -> 58198.41 | D77: =C77/$B$24 -> 0.25392811 | E77: =IF(B77=0,0,C77/B77) -> 1119.2002 | F77: =RANK(C77,$C$74:$C$77,0) -> 2
A78: Total | B78: =SUM(B74:B77) -> 250 | C78: =SUM(C74:C77) -> 229192.47 | D78: =SUM(D74:D77) -> 1
A79: Most used payment method | B79: =INDEX(A74:A77,MATCH(MAX(B74:B77),B74:B77,0)) -> Cash
A81: 8. Customer Segment (per-transaction label)
A82: Segment | B82: Orders | C82: Revenue | D82: Share | E82: Avg_Order | F82: Rev_Rank
A83: Basic | B83: =COUNTIF('Raw Data'!$L$2:$L$251,A83) -> 74 | C83: =SUMIFS('Raw Data'!$N$2:$N$251,'Raw Data'!$L$2:$L$251,A83) -> 62177.81 | D83: =C83/$B$24 -> 0.27129081 | E83: =IF(B83=0,0,C83/B83) -> 840.24068 | F83: =RANK(C83,$C$83:$C$85,0) -> 3
A84: Premium | B84: =COUNTIF('Raw Data'!$L$2:$L$251,A84) -> 95 | C84: =SUMIFS('Raw Data'!$N$2:$N$251,'Raw Data'!$L$2:$L$251,A84) -> 84657.12 | D84: =C84/$B$24 -> 0.3693713 | E84: =IF(B84=0,0,C84/B84) -> 891.12758 | F84: =RANK(C84,$C$83:$C$85,0) -> 1
A85: Standard | B85: =COUNTIF('Raw Data'!$L$2:$L$251,A85) -> 81 | C85: =SUMIFS('Raw Data'!$N$2:$N$251,'Raw Data'!$L$2:$L$251,A85) -> 82357.54 | D85: =C85/$B$24 -> 0.3593379 | E85: =IF(B85=0,0,C85/B85) -> 1016.7598 | F85: =RANK(C85,$C$83:$C$85,0) -> 2
A86: Total | B86: =SUM(B83:B85) -> 250 | C86: =SUM(C83:C85) -> 229192.47 | D86: =SUM(D83:D85) -> 1
A88: 9. Monthly Trend & Linear Regression (Revenue vs Month Index)
A89: Month_End | B89: Month | C89: Index | D89: Orders | E89: Revenue | F89: MoM_%
A90: =EOMONTH(MIN('Raw Data'!$B$2:$B$251),0) -> 45412 | B90: =TEXT(A90,"mmm-yy") -> Apr-24 | C90: 1 | D90: =COUNTIFS('Raw Data'!$P$2:$P$251,A90) -> 21 | E90: =SUMIFS('Raw Data'!$N$2:$N$251,'Raw Data'!$P$2:$P$251,A90) -> 20919.33
A91: =EOMONTH(A90,1) -> 45443 | B91: =TEXT(A91,"mmm-yy") -> May-24 | C91: =C90+1 -> 2 | D91: =COUNTIFS('Raw Data'!$P$2:$P$251,A91) -> 19 | E91: =SUMIFS('Raw Data'!$N$2:$N$251,'Raw Data'!$P$2:$P$251,A91) -> 17039.35 | F91: =IF(E90=0,"",E91/E90-1) -> -0.18547344
A92: =EOMONTH(A91,1) -> 45473 | B92: =TEXT(A92,"mmm-yy") -> Jun-24 | C92: =C91+1 -> 3 | D92: =COUNTIFS('Raw Data'!$P$2:$P$251,A92) -> 19 | E92: =SUMIFS('Raw Data'!$N$2:$N$251,'Raw Data'!$P$2:$P$251,A92) -> 19299.45 | F92: =IF(E91=0,"",E92/E91-1) -> 0.13264004
A93: =EOMONTH(A92,1) -> 45504 | B93: =TEXT(A93,"mmm-yy") -> Jul-24 | C93: =C92+1 -> 4 | D93: =COUNTIFS('Raw Data'!$P$2:$P$251,A93) -> 24 | E93: =SUMIFS('Raw Data'!$N$2:$N$251,'Raw Data'!$P$2:$P$251,A93) -> 18479.4 | F93: =IF(E92=0,"",E93/E92-1) -> -0.042490848
A94: =EOMONTH(A93,1) -> 45535 | B94: =TEXT(A94,"mmm-yy") -> Aug-24 | C94: =C93+1 -> 5 | D94: =COUNTIFS('Raw Data'!$P$2:$P$251,A94) -> 18 | E94: =SUMIFS('Raw Data'!$N$2:$N$251,'Raw Data'!$P$2:$P$251,A94) -> 15759.43 | F94: =IF(E93=0,"",E94/E93-1) -> -0.1471893
A95: =EOMONTH(A94,1) -> 45565 | B95: =TEXT(A95,"mmm-yy") -> Sep-24 | C95: =C94+1 -> 6 | D95: =COUNTIFS('Raw Data'!$P$2:$P$251,A95) -> 19 | E95: =SUMIFS('Raw Data'!$N$2:$N$251,'Raw Data'!$P$2:$P$251,A95) -> 12989.51 | F95: =IF(E94=0,"",E95/E94-1) -> -0.1757627
A96: =EOMONTH(A95,1) -> 45596 | B96: =TEXT(A96,"mmm-yy") -> Oct-24 | C96: =C95+1 -> 7 | D96: =COUNTIFS('Raw Data'!$P$2:$P$251,A96) -> 16 | E96: =SUMIFS('Raw Data'!$N$2:$N$251,'Raw Data'!$P$2:$P$251,A96) -> 20609.52 | F96: =IF(E95=0,"",E96/E95-1) -> 0.58662798
A97: =EOMONTH(A96,1) -> 45626 | B97: =TEXT(A97,"mmm-yy") -> Nov-24 | C97: =C96+1 -> 8 | D97: =COUNTIFS('Raw Data'!$P$2:$P$251,A97) -> 17 | E97: =SUMIFS('Raw Data'!$N$2:$N$251,'Raw Data'!$P$2:$P$251,A97) -> 12309.44 | F97: =IF(E96=0,"",E97/E96-1) -> -0.40273039
A98: =EOMONTH(A97,1) -> 45657 | B98: =TEXT(A98,"mmm-yy") -> Dec-24 | C98: =C97+1 -> 9 | D98: =COUNTIFS('Raw Data'!$P$2:$P$251,A98) -> 25 | E98: =SUMIFS('Raw Data'!$N$2:$N$251,'Raw Data'!$P$2:$P$251,A98) -> 23039.3 | F98: =IF(E97=0,"",E98/E97-1) -> 0.87167735
A99: =EOMONTH(A98,1) -> 45688 | B99: =TEXT(A99,"mmm-yy") -> Jan-25 | C99: =C98+1 -> 10 | D99: =COUNTIFS('Raw Data'!$P$2:$P$251,A99) -> 26 | E99: =SUMIFS('Raw Data'!$N$2:$N$251,'Raw Data'!$P$2:$P$251,A99) -> 25799.15 | F99: =IF(E98=0,"",E99/E98-1) -> 0.1197888
A100: =EOMONTH(A99,1) -> 45716 | B100: =TEXT(A100,"mmm-yy") -> Feb-25 | C100: =C99+1 -> 11 | D100: =COUNTIFS('Raw Data'!$P$2:$P$251,A100) -> 20 | E100: =SUMIFS('Raw Data'!$N$2:$N$251,'Raw Data'!$P$2:$P$251,A100) -> 16069.38 | F100: =IF(E99=0,"",E100/E99-1) -> -0.37713529
A101: =EOMONTH(A100,1) -> 45747 | B101: =TEXT(A101,"mmm-yy") -> Mar-25 | C101: =C100+1 -> 12 | D101: =COUNTIFS('Raw Data'!$P$2:$P$251,A101) -> 19 | E101: =SUMIFS('Raw Data'!$N$2:$N$251,'Raw Data'!$P$2:$P$251,A101) -> 19899.38 | F101: =IF(E100=0,"",E101/E100-1) -> 0.23834149
A102: =EOMONTH(A101,1) -> 45777 | B102: =TEXT(A102,"mmm-yy") -> Apr-25 | C102: =C101+1 -> 13 | D102: =COUNTIFS('Raw Data'!$P$2:$P$251,A102) -> 7 | E102: =SUMIFS('Raw Data'!$N$2:$N$251,'Raw Data'!$P$2:$P$251,A102) -> 6979.83 | F102: =IF(E101=0,"",E102/E101-1) -> -0.64924385
A103: Last month is partial (data ends 11-Apr-2025). It is shown in charts but excluded from the regression (rows 1–12).
A104: Regression results (formula cross-check of Data Analysis ToolPak output)
A106: Observations (months) | B106: =COUNT($E$90:$E$101) -> 12
A107: Slope (revenue change per month) | B107: =SLOPE($E$90:$E$101,$C$90:$C$101) -> 159.50441
A108: Intercept | B108: =INTERCEPT($E$90:$E$101,$C$90:$C$101) -> 17480.941
A109: R-squared | B109: =RSQ($E$90:$E$101,$C$90:$C$101) -> 0.021273185
A110: Std error of estimate | B110: =STEYX($E$90:$E$101,$C$90:$C$101) -> 4091.2421
A111: Std error of slope | B111: =INDEX(LINEST($E$90:$E$101,$C$90:$C$101,TRUE(),TRUE()),2,1) -> 342.12685
A112: t-statistic | B112: =B107/B111 -> 0.46621422
...

Sheet Customers
A1: Customers – GroupBy by Customer_ID (SUMIFS / COUNTIFS)
A2: Tier: High-Value = top 20% of spend (80th percentile), Mid = 50th–80th, Low = below median. Grouping uses Customer_ID because Region/Segment vary per transaction. | L2: Top 10 Customers | Q2: Compare Two Lists: Top-15 spenders vs Laptop buyers
A3: Customer_ID | B3: Customer_Name | C3: Total_Spend | D3: Orders | E3: Avg_Order | F3: Spend_Rank | G3: Tier | H3: Laptop_Orders | I3: Laptop_Seq | J3: Repeat_Status | L3: Rank | M3: Customer | N3: Total_Spend | O3: Share_of_Revenue | Q3: # | R3: List A: Top 15 by spend | S3: List B: Laptop buyers | T3: Matches (in both lists)
A4: CUST001 | B4: =INDEX('Raw Data'!$D$2:$D$251,MATCH(A4,'Raw Data'!$C$2:$C$251,0)) -> John Smith | C4: =SUMIFS('Raw Data'!$N$2:$N$251,'Raw Data'!$C$2:$C$251,A4) -> 599.96 | D4: =COUNTIFS('Raw Data'!$C$2:$C$251,A4) -> 1 | E4: =IF(D4=0,0,C4/D4) -> 599.96 | F4: =RANK(C4,$C$4:$C$53,0)+COUNTIF($C$4:C4,C4)-1 -> 47 | G4: =IF(C4>=PERCENTILE($C$4:$C$53,0.8),"High-Value",IF(C4>=PERCENTILE($C$4:$C$53,0.5),"Mid","Low")) -> Low | H4: =COUNTIFS('Raw Data'!$C$2:$C$251,A4,'Raw Data'!$F$2:$F$251,"Laptop") -> 0 | I4: =IF(H4>0,MAX(I$3:I3)+1,"") | J4: =IF(D4>1,"Repeat","One-time") -> One-time | L4: 1 | M4: =INDEX($B$4:$B$53,MATCH(L4,$F$4:$F$53,0)) -> Mark Carter | N4: =INDEX($C$4:$C$53,MATCH(L4,$F$4:$F$53,0)) -> 15659.65 | O4: =N4/SUM('Raw Data'!$N$2:$N$251) -> 0.068325325 | Q4: 1 | R4: =INDEX($B$4:$B$53,MATCH(Q4,$F$4:$F$53,0)) -> Mark Carter | S4: =IFERROR(INDEX($B$4:$B$53,MATCH(Q4,$I$4:$I$53,0)),"") -> Robert Thomas | T4: =IF(COUNTIF($S$4:$S$53,R4)>0,R4,"") -> Mark Carter
A5: CUST002 | B5: =INDEX('Raw Data'!$D$2:$D$251,MATCH(A5,'Raw Data'!$C$2:$C$251,0)) -> Emma Wilson | C5: =SUMIFS('Raw Data'!$N$2:$N$251,'Raw Data'!$C$2:$C$251,A5) -> 1229.88 | D5: =COUNTIFS('Raw Data'!$C$2:$C$251,A5) -> 5 | E5: =IF(D5=0,0,C5/D5) -> 245.976 | F5: =RANK(C5,$C$4:$C$53,0)+COUNTIF($C$4:C5,C5)-1 -> 44 | G5: =IF(C5>=PERCENTILE($C$4:$C$53,0.8),"High-Value",IF(C5>=PERCENTILE($C$4:$C$53,0.5),"Mid","Low")) -> Low | H5: =COUNTIFS('Raw Data'!$C$2:$C$251,A5,'Raw Data'!$F$2:$F$251,"Laptop") -> 0 | I5: =IF(H5>0,MAX(I$3:I4)+1,"") | J5: =IF(D5>1,"Repeat","One-time") -> Repeat | L5: 2 | M5: =INDEX($B$4:$B$53,MATCH(L5,$F$4:$F$53,0)) -> Edward Mitchell | N5: =INDEX($C$4:$C$53,MATCH(L5,$F$4:$F$53,0)) -> 11919.77 | O5: =N5/SUM('Raw Data'!$N$2:$N$251) -> 0.052007686 | Q5: 2 | R5: =INDEX($B$4:$B$53,MATCH(Q5,$F$4:$F$53,0)) -> Edward Mitchell | S5: =IFERROR(INDEX($B$4:$B$53,MATCH(Q5,$I$4:$I$53,0)),"") -> William White | T5: =IF(COUNTIF($S$4:$S$53,R5)>0,R5,"") -> Edward Mitchell
A6: CUST003 | B6: =INDEX('Raw Data'!$D$2:$D$251,MATCH(A6,'Raw Data'!$C$2:$C$251,0)) -> Michael Brown | C6: =SUMIFS('Raw Data'!$N$2:$N$251,'Raw Data'!$C$2:$C$251,A6) -> 6169.74 | D6: =COUNTIFS('Raw Data'!$C$2:$C$251,A6) -> 9 | E6: =IF(D6=0,0,C6/D6) -> 685.52667 | F6: =RANK(C6,$C$4:$C$53,0)+COUNTIF($C$4:C6,C6)-1 -> 14 | G6: =IF(C6>=PERCENTILE($C$4:$C$53,0.8),"High-Value",IF(C6>=PERCENTILE($C$4:$C$53,0.5),"Mid","Low")) -> Mid | H6: =COUNTIFS('Raw Data'!$C$2:$C$251,A6,'Raw Data'!$F$2:$F$251,"Laptop") -> 0 | I6: =IF(H6>0,MAX(I$3:I5)+1,"") | J6: =IF(D6>1,"Repeat","One-time") -> Repeat | L6: 3 | M6: =INDEX($B$4:$B$53,MATCH(L6,$F$4:$F$53,0)) -> Barbara Young | N6: =INDEX($C$4:$C$53,MATCH(L6,$F$4:$F$53,0)) -> 10649.8 | O6: =N6/SUM('Raw Data'!$N$2:$N$251) -> 0.046466623 | Q6: 3 | R6: =INDEX($B$4:$B$53,MATCH(Q6,$F$4:$F$53,0)) -> Barbara Young | S6: =IFERROR(INDEX($B$4:$B$53,MATCH(Q6,$I$4:$I$53,0)),"") -> Patricia Moore | T6: =IF(COUNTIF($S$4:$S$53,R6)>0,R6,"") -> Barbara Young
A7: CUST004 | B7: =INDEX('Raw Data'!$D$2:$D$251,MATCH(A7,'Raw Data'!$C$2:$C$251,0)) -> Sarah Davis | C7: =SUMIFS('Raw Data'!$N$2:$N$251,'Raw Data'!$C$2:$C$251,A7) -> 5499.81 | D7: =COUNTIFS('Raw Data'!$C$2:$C$251,A7) -> 5 | E7: =IF(D7=0,0,C7/D7) -> 1099.962 | F7: =RANK(C7,$C$4:$C$53,0)+COUNTIF($C$4:C7,C7)-1 -> 19 | G7: =IF(C7>=PERCENTILE($C$4:$C$53,0.8),"High-Value",IF(C7>=PERCENTILE($C$4:$C$53,0.5),"Mid","Low")) -> Mid | H7: =COUNTIFS('Raw Data'!$C$2:$C$251,A7,'Raw Data'!$F$2:$F$251,"Laptop") -> 0 | I7: =IF(H7>0,MAX(I$3:I6)+1,"") | J7: =IF(D7>1,"Repeat","One-time") -> Repeat | L7: 4 | M7: =INDEX($B$4:$B$53,MATCH(L7,$F$4:$F$53,0)) -> Patricia Moore | N7: =INDEX($C$4:$C$53,MATCH(L7,$F$4:$F$53,0)) -> 9799.73 | O7: =N7/SUM('Raw Data'!$N$2:$N$251) -> 0.042757644 | Q7: 4 | R7: =INDEX($B$4:$B$53,MATCH(Q7,$F$4:$F$53,0)) -> Patricia Moore | S7: =IFERROR(INDEX($B$4:$B$53,MATCH(Q7,$I$4:$I$53,0)),"") -> Joseph Jackson | T7: =IF(COUNTIF($S$4:$S$53,R7)>0,R7,"") -> Patricia Moore
A8: CUST005 | B8: =INDEX('Raw Data'!$D$2:$D$251,MATCH(A8,'Raw Data'!$C$2:$C$251,0)) -> James Johnson | C8: =SUMIFS('Raw Data'!$N$2:$N$251,'Raw Data'!$C$2:$C$251,A8) -> 179.97 | D8: =COUNTIFS('Raw Data'!$C$2:$C$251,A8) -> 1 | E8: =IF(D8=0,0,C8/D8) -> 179.97 | F8: =RANK(C8,$C$4:$C$53,0)+COUNTIF($C$4:C8,C8)-1 -> 50 | G8: =IF(C8>=PERCENTILE($C$4:$C$53,0.8),"High-Value",IF(C8>=PERCENTILE($C$4:$C$53,0.5),"Mid","Low")) -> Low | H8: =COUNTIFS('Raw Data'!$C$2:$C$251,A8,'Raw Data'!$F$2:$F$251,"Laptop") -> 0 | I8: =IF(H8>0,MAX(I$3:I7)+1,"") | J8: =IF(D8>1,"Repeat","One-time") -> One-time | L8: 5 | M8: =INDEX($B$4:$B$53,MATCH(L8,$F$4:$F$53,0)) -> Paul Baker | N8: =INDEX($C$4:$C$53,MATCH(L8,$F$4:$F$53,0)) -> 8309.74 | O8: =N8/SUM('Raw Data'!$N$2:$N$251) -> 0.036256601 | Q8: 5 | R8: =INDEX($B$4:$B$53,MATCH(Q8,$F$4:$F$53,0)) -> Paul Baker | S8: =IFERROR(INDEX($B$4:$B$53,MATCH(Q8,$I$4:$I$53,0)),"") -> Barbara Young | T8: =IF(COUNTIF($S$4:$S$53,R8)>0,R8,"") -> Paul Baker
A9: CUST006 | B9: =INDEX('Raw Data'!$D$2:$D$251,MATCH(A9,'Raw Data'!$C$2:$C$251,0)) -> Lisa Anderson | C9: =SUMIFS('Raw Data'!$N$2:$N$251,'Raw Data'!$C$2:$C$251,A9) -> 2039.8 | D9: =COUNTIFS('Raw Data'!$C$2:$C$251,A9) -> 5 | E9: =IF(D9=0,0,C9/D9) -> 407.96 | F9: =RANK(C9,$C$4:$C$53,0)+COUNTIF($C$4:C9,C9)-1 -> 36 | G9: =IF(C9>=PERCENTILE($C$4:$C$53,0.8),"High-Value",IF(C9>=PERCENTILE($C$4:$C$53,0.5),"Mid","Low")) -> Low | H9: =COUNTIFS('Raw Data'!$C$2:$C$251,A9,'Raw Data'!$F$2:$F$251,"Laptop") -> 0 | I9: =IF(H9>0,MAX(I$3:I8)+1,"") | J9: =IF(D9>1,"Repeat","One-time") -> Repeat | L9: 6 | M9: =INDEX($B$4:$B$53,MATCH(L9,$F$4:$F$53,0)) -> Dorothy Nelson | N9: =INDEX($C$4:$C$53,MATCH(L9,$F$4:$F$53,0)) -> 8269.79 | O9: =N9/SUM('Raw Data'!$N$2:$N$251) -> 0.036082294 | Q9: 6 | R9: =INDEX($B$4:$B$53,MATCH(Q9,$F$4:$F$53,0)) -> Dorothy Nelson | S9: =IFERROR(INDEX($B$4:$B$53,MATCH(Q9,$I$4:$I$53,0)),"") -> Daniel King | T9: =IF(COUNTIF($S$4:$S$53,R9)>0,R9,"") -> Dorothy Nelson
A10: CUST007 | B10: =INDEX('Raw Data'!$D$2:$D$251,MATCH(A10,'Raw Data'!$C$2:$C$251,0)) -> David Martinez | C10: =SUMIFS('Raw Data'!$N$2:$N$251,'Raw Data'!$C$2:$C$251,A10) -> 1809.84 | D10: =COUNTIFS('Raw Data'!$C$2:$C$251,A10) -> 6 | E10: =IF(D10=0,0,C10/D10) -> 301.64 | F10: =RANK(C10,$C$4:$C$53,0)+COUNTIF($C$4:C10,C10)-1 -> 39 | G10: =IF(C10>=PERCENTILE($C$4:$C$53,0.8),"High-Value",IF(C10>=PERCENTILE($C$4:$C$53,0.5),"Mid","Low")) -> Low | H10: =COUNTIFS('Raw Data'!$C$2:$C$251,A10,'Raw Data'!$F$2:$F$251,"Laptop") -> 0 | I10: =IF(H10>0,MAX(I$3:I9)+1,"") | J10: =IF(D10>1,"Repeat","One-time") -> Repeat | L10: 7 | M10: =INDEX($B$4:$B$53,MATCH(L10,$F$4:$F$53,0)) -> Karen Hill | N10: =INDEX($C$4:$C$53,MATCH(L10,$F$4:$F$53,0)) -> 8009.77 | O10: =N10/SUM('Raw Data'!$N$2:$N$251) -> 0.034947789 | Q10: 7 | R10: =INDEX($B$4:$B$53,MATCH(Q10,$F$4:$F$53,0)) -> Karen Hill | S10: =IFERROR(INDEX($B$4:$B$53,MATCH(Q10,$I$4:$I$53,0)),"") -> Kevin Scott | T10: =IF(COUNTIF($S$4:$S$53,R10)>0,R10,"")
A11: CUST008 | B11: =INDEX('Raw Data'!$D$2:$D$251,MATCH(A11,'Raw Data'!$C$2:$C$251,0)) -> Jennifer Taylor | C11: =SUMIFS('Raw Data'!$N$2:$N$251,'Raw Data'!$C$2:$C$251,A11) -> 4739.85 | D11: =COUNTIFS('Raw Data'!$C$2:$C$251,A11) -> 4 | E11: =IF(D11=0,0,C11/D11) -> 1184.9625 | F11: =RANK(C11,$C$4:$C$53,0)+COUNTIF($C$4:C11,C11)-1 -> 24 | G11: =IF(C11>=PERCENTILE($C$4:$C$53,0.8),"High-Value",IF(C11>=PERCENTILE($C$4:$C$53,0.5),"Mid","Low")) -> Mid | H11: =COUNTIFS('Raw Data'!$C$2:$C$251,A11,'Raw Data'!$F$2:$F$251,"Laptop") -> 0 | I11: =IF(H11>0,MAX(I$3:I10)+1,"") | J11: =IF(D11>1,"Repeat","One-time") -> Repeat | L11: 8 | M11: =INDEX($B$4:$B$53,MATCH(L11,$F$4:$F$53,0)) -> Daniel King | N11: =INDEX($C$4:$C$53,MATCH(L11,$F$4:$F$53,0)) -> 7309.8 | O11: =N11/SUM('Raw Data'!$N$2:$N$251) -> 0.031893718 | Q11: 8 | R11: =INDEX($B$4:$B$53,MATCH(Q11,$F$4:$F$53,0)) -> Daniel King | S11: =IFERROR(INDEX($B$4:$B$53,MATCH(Q11,$I$4:$I$53,0)),"") -> Paul Baker | T11: =IF(COUNTIF($S$4:$S$53,R11)>0,R11,"") -> Daniel King
A12: CUST009 | B12: =INDEX('Raw Data'!$D$2:$D$251,MATCH(A12,'Raw Data'!$C$2:$C$251,0)) -> Robert Thomas | C12: =SUMIFS('Raw Data'!$N$2:$N$251,'Raw Data'!$C$2:$C$251,A12) -> 3509.9 | D12: =COUNTIFS('Raw Data'!$C$2:$C$251,A12) -> 5 | E12: =IF(D12=0,0,C12/D12) -> 701.98 | F12: =RANK(C12,$C$4:$C$53,0)+COUNTIF($C$4:C12,C12)-1 -> 32 | G12: =IF(C12>=PERCENTILE($C$4:$C$53,0.8),"High-Value",IF(C12>=PERCENTILE($C$4:$C$53,0.5),"Mid","Low")) -> Low | H12: =COUNTIFS('Raw Data'!$C$2:$C$251,A12,'Raw Data'!$F$2:$F$251,"Laptop") -> 1 | I12: =IF(H12>0,MAX(I$3:I11)+1,"") -> 1 | J12: =IF(D12>1,"Repeat","One-time") -> Repeat | L12: 9 | M12: =INDEX($B$4:$B$53,MATCH(L12,$F$4:$F$53,0)) -> Lawrence Reed | N12: =INDEX($C$4:$C$53,MATCH(L12,$F$4:$F$53,0)) -> 6989.77 | O12: =N12/SUM('Raw Data'!$N$2:$N$251) -> 0.030497381 | Q12: 9 | R12: =INDEX($B$4:$B$53,MATCH(Q12,$F$4:$F$53,0)) -> Lawrence Reed | S12: =IFERROR(INDEX($B$4:$B$53,MATCH(Q12,$I$4:$I$53,0)),"") -> Dorothy Nelson | T12: =IF(COUNTIF($S$4:$S$53,R12)>0,R12,"")
A13: CUST010 | B13: =INDEX('Raw Data'!$D$2:$D$251,MATCH(A13,'Raw Data'!$C$2:$C$251,0)) -> Maria Garcia | C13: =SUMIFS('Raw Data'!$N$2:$N$251,'Raw Data'!$C$2:$C$251,A13) -> 1909.93 | D13: =COUNTIFS('Raw Data'!$C$2:$C$251,A13) -> 4 | E13: =IF(D13=0,0,C13/D13) -> 477.4825 | F13: =RANK(C13,$C$4:$C$53,0)+COUNTIF($C$4:C13,C13)-1 -> 38 | G13: =IF(C13>=PERCENTILE($C$4:$C$53,0.8),"High-Value",IF(C13>=PERCENTILE($C$4:$C$53,0.5),"Mid","Low")) -> Low | H13: =COUNTIFS('Raw Data'!$C$2:$C$251,A13,'Raw Data'!$F$2:$F$251,"Laptop") -> 0 | I13: =IF(H13>0,MAX(I$3:I12)+1,"") | J13: =IF(D13>1,"Repeat","One-time") -> Repeat | L13: 10 | M13: =INDEX($B$4:$B$53,MATCH(L13,$F$4:$F$53,0)) -> Joseph Jackson | N13: =INDEX($C$4:$C$53,MATCH(L13,$F$4:$F$53,0)) -> 6949.84 | O13: =N13/SUM('Raw Data'!$N$2:$N$251) -> 0.03032316 | Q13: 10 | R13: =INDEX($B$4:$B$53,MATCH(Q13,$F$4:$F$53,0)) -> Joseph Jackson | S13: =IFERROR(INDEX($B$4:$B$53,MATCH(Q13,$I$4:$I$53,0)),"") -> Mark Carter | T13: =IF(COUNTIF($S$4:$S$53,R13)>0,R13,"") -> Joseph Jackson
A14: CUST011 | B14: =INDEX('Raw Data'!$D$2:$D$251,MATCH(A14,'Raw Data'!$C$2:$C$251,0)) -> William White | C14: =SUMIFS('Raw Data'!$N$2:$N$251,'Raw Data'!$C$2:$C$251,A14) -> 4749.91 | D14: =COUNTIFS('Raw Data'!$C$2:$C$251,A14) -> 3 | E14: =IF(D14=0,0,C14/D14) -> 1583.3033 | F14: =RANK(C14,$C$4:$C$53,0)+COUNTIF($C$4:C14,C14)-1 -> 23 | G14: =IF(C14>=PERCENTILE($C$4:$C$53,0.8),"High-Value",IF(C14>=PERCENTILE($C$4:$C$53,0.5),"Mid","Low")) -> Mid | H14: =COUNTIFS('Raw Data'!$C$2:$C$251,A14,'Raw Data'!$F$2:$F$251,"Laptop") -> 1 | I14: =IF(H14>0,MAX(I$3:I13)+1,"") -> 2 | J14: =IF(D14>1,"Repeat","One-time") -> Repeat | Q14: 11 | R14: =INDEX($B$4:$B$53,MATCH(Q14,$F$4:$F$53,0)) -> Helen Roberts | S14: =IFERROR(INDEX($B$4:$B$53,MATCH(Q14,$I$4:$I$53,0)),"") -> George Adams | T14: =IF(COUNTIF($S$4:$S$53,R14)>0,R14,"") -> Helen Roberts
A15: CUST012 | B15: =INDEX('Raw Data'!$D$2:$D$251,MATCH(A15,'Raw Data'!$C$2:$C$251,0)) -> Patricia Moore | C15: =SUMIFS('Raw Data'!$N$2:$N$251,'Raw Data'!$C$2:$C$251,A15) -> 9799.73 | D15: =COUNTIFS('Raw Data'!$C$2:$C$251,A15) -> 8 | E15: =IF(D15=0,0,C15/D15) -> 1224.9662 | F15: =RANK(C15,$C$4:$C$53,0)+COUNTIF($C$4:C15,C15)-1 -> 4 | G15: =IF(C15>=PERCENTILE($C$4:$C$53,0.8),"High-Value",IF(C15>=PERCENTILE($C$4:$C$53,0.5),"Mid","Low")) -> High-Value | H15: =COUNTIFS('Raw Data'!$C$2:$C$251,A15,'Raw Data'!$F$2:$F$251,"Laptop") -> 1 | I15: =IF(H15>0,MAX(I$3:I14)+1,"") -> 3 | J15: =IF(D15>1,"Repeat","One-time") -> Repeat | Q15: 12 | R15: =INDEX($B$4:$B$53,MATCH(Q15,$F$4:$F$53,0)) -> Gerald Murphy | S15: =IFERROR(INDEX($B$4:$B$53,MATCH(Q15,$I$4:$I$53,0)),"") -> Edward Mitchell | T15: =IF(COUNTIF($S$4:$S$53,R15)>0,R15,"") -> Gerald Murphy
A16: CUST013 | B16: =INDEX('Raw Data'!$D$2:$D$251,MATCH(A16,'Raw Data'!$C$2:$C$251,0)) -> Joseph Jackson | C16: =SUMIFS('Raw Data'!$N$2:$N$251,'Raw Data'!$C$2:$C$251,A16) -> 6949.84 | D16: =COUNTIFS('Raw Data'!$C$2:$C$251,A16) -> 5 | E16: =IF(D16=0,0,C16/D16) -> 1389.968 | F16: =RANK(C16,$C$4:$C$53,0)+COUNTIF($C$4:C16,C16)-1 -> 10 | G16: =IF(C16>=PERCENTILE($C$4:$C$53,0.8),"High-Value",IF(C16>=PERCENTILE($C$4:$C$53,0.5),"Mid","Low")) -> High-Value | H16: =COUNTIFS('Raw Data'!$C$2:$C$251,A16,'Raw Data'!$F$2:$F$251,"Laptop") -> 1 | I16: =IF(H16>0,MAX(I$3:I15)+1,"") -> 4 | J16: =IF(D16>1,"Repeat","One-time") -> Repeat | Q16: 13 | R16: =INDEX($B$4:$B$53,MATCH(Q16,$F$4:$F$53,0)) -> Sandra Phillips | S16: =IFERROR(INDEX($B$4:$B$53,MATCH(Q16,$I$4:$I$53,0)),"") -> Helen Roberts | T16: =IF(COUNTIF($S$4:$S$53,R16)>0,R16,"") -> Sandra Phillips
A17: CUST014 | B17: =INDEX('Raw Data'!$D$2:$D$251,MATCH(A17,'Raw Data'!$C$2:$C$251,0)) -> Linda Martin | C17: =SUMIFS('Raw Data'!$N$2:$N$251,'Raw Data'!$C$2:$C$251,A17) -> 1289.9 | D17: =COUNTIFS('Raw Data'!$C$2:$C$251,A17) -> 4 | E17: =IF(D17=0,0,C17/D17) -> 322.475 | F17: =RANK(C17,$C$4:$C$53,0)+COUNTIF($C$4:C17,C17)-1 -> 43 | G17: =IF(C17>=PERCENTILE($C$4:$C$53,0.8),"High-Value",IF(C17>=PERCENTILE($C$4:$C$53,0.5),"Mid","Low")) -> Low | H17: =COUNTIFS('Raw Data'!$C$2:$C$251,A17,'Raw Data'!$F$2:$F$251,"Laptop") -> 0 | I17: =IF(H17>0,MAX(I$3:I16)+1,"") | J17: =IF(D17>1,"Repeat","One-time") -> Repeat | Q17: 14 | R17: =INDEX($B$4:$B$53,MATCH(Q17,$F$4:$F$53,0)) -> Michael Brown | S17: =IFERROR(INDEX($B$4:$B$53,MATCH(Q17,$I$4:$I$53,0)),"") -> Sandra Phillips | T17: =IF(COUNTIF($S$4:$S$53,R17)>0,R17,"")
A18: CUST015 | B18: =INDEX('Raw Data'!$D$2:$D$251,MATCH(A18,'Raw Data'!$C$2:$C$251,0)) -> Richard Lee | C18: =SUMIFS('Raw Data'!$N$2:$N$251,'Raw Data'!$C$2:$C$251,A18) -> 739.93 | D18: =COUNTIFS('Raw Data'!$C$2:$C$251,A18) -> 3 | E18: =IF(D18=0,0,C18/D18) -> 246.64333 | F18: =RANK(C18,$C$4:$C$53,0)+COUNTIF($C$4:C18,C18)-1 -> 46 | G18: =IF(C18>=PERCENTILE($C$4:$C$53,0.8),"High-Value",IF(C18>=PERCENTILE($C$4:$C$53,0.5),"Mid","Low")) -> Low | H18: =COUNTIFS('Raw Data'!$C$2:$C$251,A18,'Raw Data'!$F$2:$F$251,"Laptop") -> 0 | I18: =IF(H18>0,MAX(I$3:I17)+1,"") | J18: =IF(D18>1,"Repeat","One-time") -> Repeat | Q18: 15 | R18: =INDEX($B$4:$B$53,MATCH(Q18,$F$4:$F$53,0)) -> Peter Richardson | S18: =IFERROR(INDEX($B$4:$B$53,MATCH(Q18,$I$4:$I$53,0)),"") -> Harry Morgan | T18: =IF(COUNTIF($S$4:$S$53,R18)>0,R18,"") -> Peter Richardson
A19: CUST016 | B19: =INDEX('Raw Data'!$D$2:$D$251,MATCH(A19,'Raw Data'!$C$2:$C$251,0)) -> Elizabeth Hall | C19: =SUMIFS('Raw Data'!$N$2:$N$251,'Raw Data'!$C$2:$C$251,A19) -> 3649.86 | D19: =COUNTIFS('Raw Data'!$C$2:$C$251,A19) -> 4 | E19: =IF(D19=0,0,C19/D19) -> 912.465 | F19: =RANK(C19,$C$4:$C$53,0)+COUNTIF($C$4:C19,C19)-1 -> 31 | G19: =IF(C19>=PERCENTILE($C$4:$C$53,0.8),"High-Value",IF(C19>=PERCENTILE($C$4:$C$53,0.5),"Mid","Low")) -> Low | H19: =COUNTIFS('Raw Data'!$C$2:$C$251,A19,'Raw Data'!$F$2:$F$251,"Laptop") -> 0 | I19: =IF(H19>0,MAX(I$3:I18)+1,"") | J19: =IF(D19>1,"Repeat","One-time") -> Repeat | Q19: 16 | S19: =IFERROR(INDEX($B$4:$B$53,MATCH(Q19,$I$4:$I$53,0)),"") -> Arthur Edwards
A20: CUST017 | B20: =INDEX('Raw Data'!$D$2:$D$251,MATCH(A20,'Raw Data'!$C$2:$C$251,0)) -> Charles Allen | C20: =SUMIFS('Raw Data'!$N$2:$N$251,'Raw Data'!$C$2:$C$251,A20) -> 5089.73 | D20: =COUNTIFS('Raw Data'!$C$2:$C$251,A20) -> 9 | E20: =IF(D20=0,0,C20/D20) -> 565.52556 | F20: =RANK(C20,$C$4:$C$53,0)+COUNTIF($C$4:C20,C20)-1 -> 20 | G20: =IF(C20>=PERCENTILE($C$4:$C$53,0.8),"High-Value",IF(C20>=PERCENTILE($C$4:$C$53,0.5),"Mid","Low")) -> Mid | H20: =COUNTIFS('Raw Data'!$C$2:$C$251,A20,'Raw Data'!$F$2:$F$251,"Laptop") -> 0 | I20: =IF(H20>0,MAX(I$3:I19)+1,"") | J20: =IF(D20>1,"Repeat","One-time") -> Repeat | Q20: 17 | S20: =IFERROR(INDEX($B$4:$B$53,MATCH(Q20,$I$4:$I$53,0)),"") -> Sharon Butler
A21: CUST018 | B21: =INDEX('Raw Data'!$D$2:$D$251,MATCH(A21,'Raw Data'!$C$2:$C$251,0)) -> Barbara Young | C21: =SUMIFS('Raw Data'!$N$2:$N$251,'Raw Data'!$C$2:$C$251,A21) -> 10649.8 | D21: =COUNTIFS('Raw Data'!$C$2:$C$251,A21) -> 5 | E21: =IF(D21=0,0,C21/D21) -> 2129.96 | F21: =RANK(C21,$C$4:$C$53,0)+COUNTIF($C$4:C21,C21)-1 -> 3 | G21: =IF(C21>=PERCENTILE($C$4:$C$53,0.8),"High-Value",IF(C21>=PERCENTILE($C$4:$C$53,0.5),"Mid","Low")) -> High-Value | H21: =COUNTIFS('Raw Data'!$C$2:$C$251,A21,'Raw Data'!$F$2:$F$251,"Laptop") -> 1 | I21: =IF(H21>0,MAX(I$3:I20)+1,"") -> 5 | J21: =IF(D21>1,"Repeat","One-time") -> Repeat | Q21: 18 | S21: =IFERROR(INDEX($B$4:$B$53,MATCH(Q21,$I$4:$I$53,0)),"") -> Peter Richardson
A22: CUST019 | B22: =INDEX('Raw Data'!$D$2:$D$251,MATCH(A22,'Raw Data'!$C$2:$C$251,0)) -> Daniel King | C22: =SUMIFS('Raw Data'!$N$2:$N$251,'Raw Data'!$C$2:$C$251,A22) -> 7309.8 | D22: =COUNTIFS('Raw Data'!$C$2:$C$251,A22) -> 7 | E22: =IF(D22=0,0,C22/D22) -> 1044.2571 | F22: =RANK(C22,$C$4:$C$53,0)+COUNTIF($C$4:C22,C22)-1 -> 8 | G22: =IF(C22>=PERCENTILE($C$4:$C$53,0.8),"High-Value",IF(C22>=PERCENTILE($C$4:$C$53,0.5),"Mid","Low")) -> High-Value | H22: =COUNTIFS('Raw Data'!$C$2:$C$251,A22,'Raw Data'!$F$2:$F$251,"Laptop") -> 1 | I22: =IF(H22>0,MAX(I$3:I21)+1,"") -> 6 | J22: =IF(D22>1,"Repeat","One-time") -> Repeat | Q22: 19 | S22: =IFERROR(INDEX($B$4:$B$53,MATCH(Q22,$I$4:$I$53,0)),"") -> Gerald Murphy
A23: CUST020 | B23: =INDEX('Raw Data'!$D$2:$D$251,MATCH(A23,'Raw Data'!$C$2:$C$251,0)) -> Margaret Wright | C23: =SUMIFS('Raw Data'!$N$2:$N$251,'Raw Data'!$C$2:$C$251,A23) -> 2099.88 | D23: =COUNTIFS('Raw Data'!$C$2:$C$251,A23) -> 4 | E23: =IF(D23=0,0,C23/D23) -> 524.97 | F23: =RANK(C23,$C$4:$C$53,0)+COUNTIF($C$4:C23,C23)-1 -> 35 | G23: =IF(C23>=PERCENTILE($C$4:$C$53,0.8),"High-Value",IF(C23>=PERCENTILE($C$4:$C$53,0.5),"Mid","Low")) -> Low | H23: =COUNTIFS('Raw Data'!$C$2:$C$251,A23,'Raw Data'!$F$2:$F$251,"Laptop") -> 0 | I23: =IF(H23>0,MAX(I$3:I22)+1,"") | J23: =IF(D23>1,"Repeat","One-time") -> Repeat | Q23: 20 | S23: =IFERROR(INDEX($B$4:$B$53,MATCH(Q23,$I$4:$I$53,0)),"")
A24: CUST021 | B24: =INDEX('Raw Data'!$D$2:$D$251,MATCH(A24,'Raw Data'!$C$2:$C$251,0)) -> Kevin Scott | C24: =SUMIFS('Raw Data'!$N$2:$N$251,'Raw Data'!$C$2:$C$251,A24) -> 3259.87 | D24: =COUNTIFS('Raw Data'!$C$2:$C$251,A24) -> 6 | E24: =IF(D24=0,0,C24/D24) -> 543.31167 | F24: =RANK(C24,$C$4:$C$53,0)+COUNTIF($C$4:C24,C24)-1 -> 33 | G24: =IF(C24>=PERCENTILE($C$4:$C$53,0.8),"High-Value",IF(C24>=PERCENTILE($C$4:$C$53,0.5),"Mid","Low")) -> Low | H24: =COUNTIFS('Raw Data'!$C$2:$C$251,A24,'Raw Data'!$F$2:$F$251,"Laptop") -> 1 | I24: =IF(H24>0,MAX(I$3:I23)+1,"") -> 7 | J24: =IF(D24>1,"Repeat","One-time") -> Repeat | Q24: 21 | S24: =IFERROR(INDEX($B$4:$B$53,MATCH(Q24,$I$4:$I$53,0)),"")
A25: CUST022 | B25: =INDEX('Raw Data'!$D$2:$D$251,MATCH(A25,'Raw Data'!$C$2:$C$251,0)) -> Susan Green | C25: =SUMIFS('Raw Data'!$N$2:$N$251,'Raw Data'!$C$2:$C$251,A25) -> 1979.89 | D25: =COUNTIFS('Raw Data'!$C$2:$C$251,A25) -> 4 | E25: =IF(D25=0,0,C25/D25) -> 494.9725 | F25: =RANK(C25,$C$4:$C$53,0)+COUNTIF($C$4:C25,C25)-1 -> 37 | G25: =IF(C25>=PERCENTILE($C$4:$C$53,0.8),"High-Value",IF(C25>=PERCENTILE($C$4:$C$53,0.5),"Mid","Low")) -> Low | H25: =COUNTIFS('Raw Data'!$C$2:$C$251,A25,'Raw Data'!$F$2:$F$251,"Laptop") -> 0 | I25: =IF(H25>0,MAX(I$3:I24)+1,"") | J25: =IF(D25>1,"Repeat","One-time") -> Repeat | Q25: 22 | S25: =IFERROR(INDEX($B$4:$B$53,MATCH(Q25,$I$4:$I$53,0)),"")
A26: CUST023 | B26: =INDEX('Raw Data'!$D$2:$D$251,MATCH(A26,'Raw Data'!$C$2:$C$251,0)) -> Paul Baker | C26: =SUMIFS('Raw Data'!$N$2:$N$251,'Raw Data'!$C$2:$C$251,A26) -> 8309.74 | D26: =COUNTIFS('Raw Data'!$C$2:$C$251,A26) -> 8 | E26: =IF(D26=0,0,C26/D26) -> 1038.7175 | F26: =RANK(C26,$C$4:$C$53,0)+COUNTIF($C$4:C26,C26)-1 -> 5 | G26: =IF(C26>=PERCENTILE($C$4:$C$53,0.8),"High-Value",IF(C26>=PERCENTILE($C$4:$C$53,0.5),"Mid","Low")) -> High-Value | H26: =COUNTIFS('Raw Data'!$C$2:$C$251,A26,'Raw Data'!$F$2:$F$251,"Laptop") -> 1 | I26: =IF(H26>0,MAX(I$3:I25)+1,"") -> 8 | J26: =IF(D26>1,"Repeat","One-time") -> Repeat | Q26: 23 | S26: =IFERROR(INDEX($B$4:$B$53,MATCH(Q26,$I$4:$I$53,0)),"")
A27: CUST024 | B27: =INDEX('Raw Data'!$D$2:$D$251,MATCH(A27,'Raw Data'!$C$2:$C$251,0)) -> Dorothy Nelson | C27: =SUMIFS('Raw Data'!$N$2:$N$251,'Raw Data'!$C$2:$C$251,A27) -> 8269.79 | D27: =COUNTIFS('Raw Data'!$C$2:$C$251,A27) -> 6 | E27: =IF(D27=0,0,C27/D27) -> 1378.2983 | F27: =RANK(C27,$C$4:$C$53,0)+COUNTIF($C$4:C27,C27)-1 -> 6 | G27: =IF(C27>=PERCENTILE($C$4:$C$53,0.8),"High-Value",IF(C27>=PERCENTILE($C$4:$C$53,0.5),"Mid","Low")) -> High-Value | H27: =COUNTIFS('Raw Data'!$C$2:$C$251,A27,'Raw Data'!$F$2:$F$251,"Laptop") -> 1 | I27: =IF(H27>0,MAX(I$3:I26)+1,"") -> 9 | J27: =IF(D27>1,"Repeat","One-time") -> Repeat | Q27: 24 | S27: =IFERROR(INDEX($B$4:$B$53,MATCH(Q27,$I$4:$I$53,0)),"")
A28: CUST025 | B28: =INDEX('Raw Data'!$D$2:$D$251,MATCH(A28,'Raw Data'!$C$2:$C$251,0)) -> Mark Carter | C28: =SUMIFS('Raw Data'!$N$2:$N$251,'Raw Data'!$C$2:$C$251,A28) -> 15659.65 | D28: =COUNTIFS('Raw Data'!$C$2:$C$251,A28) -> 12 | E28: =IF(D28=0,0,C28/D28) -> 1304.9708 | F28: =RANK(C28,$C$4:$C$53,0)+COUNTIF($C$4:C28,C28)-1 -> 1 | G28: =IF(C28>=PERCENTILE($C$4:$C$53,0.8),"High-Value",IF(C28>=PERCENTILE($C$4:$C$53,0.5),"Mid","Low")) -> High-Value | H28: =COUNTIFS('Raw Data'!$C$2:$C$251,A28,'Raw Data'!$F$2:$F$251,"Laptop") -> 2 | I28: =IF(H28>0,MAX(I$3:I27)+1,"") -> 10 | J28: =IF(D28>1,"Repeat","One-time") -> Repeat | Q28: 25 | S28: =IFERROR(INDEX($B$4:$B$53,MATCH(Q28,$I$4:$I$53,0)),"")
A29: CUST026 | B29: =INDEX('Raw Data'!$D$2:$D$251,MATCH(A29,'Raw Data'!$C$2:$C$251,0)) -> Karen Hill | C29: =SUMIFS('Raw Data'!$N$2:$N$251,'Raw Data'!$C$2:$C$251,A29) -> 8009.77 | D29: =COUNTIFS('Raw Data'!$C$2:$C$251,A29) -> 8 | E29: =IF(D29=0,0,C29/D29) -> 1001.2212 | F29: =RANK(C29,$C$4:$C$53,0)+COUNTIF($C$4:C29,C29)-1 -> 7 | G29: =IF(C29>=PERCENTILE($C$4:$C$53,0.8),"High-Value",IF(C29>=PERCENTILE($C$4:$C$53,0.5),"Mid","Low")) -> High-Value | H29: =COUNTIFS('Raw Data'!$C$2:$C$251,A29,'Raw Data'!$F$2:$F$251,"Laptop") -> 0 | I29: =IF(H29>0,MAX(I$3:I28)+1,"") | J29: =IF(D29>1,"Repeat","One-time") -> Repeat | Q29: 26 | S29: =IFERROR(INDEX($B$4:$B$53,MATCH(Q29,$I$4:$I$53,0)),"")
A30: CUST027 | B30: =INDEX('Raw Data'!$D$2:$D$251,MATCH(A30,'Raw Data'!$C$2:$C$251,0)) -> George Adams | C30: =SUMIFS('Raw Data'!$N$2:$N$251,'Raw Data'!$C$2:$C$251,A30) -> 3779.93 | D30: =COUNTIFS('Raw Data'!$C$2:$C$251,A30) -> 3 | E30: =IF(D30=0,0,C30/D30) -> 1259.9767 | F30: =RANK(C30,$C$4:$C$53,0)+COUNTIF($C$4:C30,C30)-1 -> 28 | G30: =IF(C30>=PERCENTILE($C$4:$C$53,0.8),"High-Value",IF(C30>=PERCENTILE($C$4:$C$53,0.5),"Mid","Low")) -> Low | H30: =COUNTIFS('Raw Data'!$C$2:$C$251,A30,'Raw Data'!$F$2:$F$251,"Laptop") -> 2 | I30: =IF(H30>0,MAX(I$3:I29)+1,"") -> 11 | J30: =IF(D30>1,"Repeat","One-time") -> Repeat | Q30: 27 | S30: =IFERROR(INDEX($B$4:$B$53,MATCH(Q30,$I$4:$I$53,0)),"")
... A53: CUST050 | B53: =INDEX('Raw Data'!$D$2:$D$251,MATCH(A53,'Raw Data'!$C$2:$C$251,0)) -> Julie Foster | C53: =SUMIFS('Raw Data'!$N$2:$N$251,'Raw Data'!$C$2:$C$251,A53) -> 239.96 | D53: =COUNTIFS('Raw Data'!$C$2:$C$251,A53) -> 1 | E53: =IF(D53=0,0,C53/D53) -> 239.96 | F53: =RANK(C53,$C$4:$C$53,0)+COUNTIF($C$4:C53,C53)-1 -> 49 | G53: =IF(C53>=PERCENTILE($C$4:$C$53,0.8),"High-Value",IF(C53>=PERCENTILE($C$4:$C$53,0.5),"Mid","Low")) -> Low | H53: =COUNTIFS('Raw Data'!$C$2:$C$251,A53,'Raw Data'!$F$2:$F$251,"Laptop") -> 0 | I53: =IF(H53>0,MAX(I$3:I52)+1,"") | J53: =IF(D53>1,"Repeat","One-time") -> One-time | Q53: 50 | S53: =IFERROR(INDEX($B$4:$B$53,MATCH(Q53,$I$4:$I$53,0)),"")
Q55: Matches found | S55: =COUNTIF(T4:T18,"?*") -> 12

Sheet Filter
A1: FILTER demo – multi-value return
A4: Region | B4: West
A5: Min Total_Amount ($) | B5: 1000
A6: Matching rows | B6: =COUNT('Raw Data'!$Y$2:$Y$251) -> 12
A8: Excel 365 one-cell equivalent (paste into any empty cell):
A9: FILTER formula: =FILTER(tblSales[[Transaction_ID]:[Total_Amount]],(tblSales[Region]=B4)*(tblSales[Total_Amount]>=B5),"No matching records")
A10: # | B10: Transaction_ID | C10: Date | D10: Customer | E10: Product | F10: Qty | G10: Total_Amount | H10: Region
A11: 1 | B11: =IFERROR(INDEX('Raw Data'!$A$2:$A$251,MATCH($A11,'Raw Data'!$Y$2:$Y$251,0)),"") -> TRX0191 | C11: =IFERROR(INDEX('Raw Data'!$B$2:$B$251,MATCH($A11,'Raw Data'!$Y$2:$Y$251,0)),"") -> 45409 | D11: =IFERROR(INDEX('Raw Data'!$D$2:$D$251,MATCH($A11,'Raw Data'!$Y$2:$Y$251,0)),"") -> Michelle Rogers | E11: =IFERROR(INDEX('Raw Data'!$F$2:$F$251,MATCH($A11,'Raw Data'!$Y$2:$Y$251,0)),"") -> Smartphone | F11: =IFERROR(INDEX('Raw Data'!$H$2:$H$251,MATCH($A11,'Raw Data'!$Y$2:$Y$251,0)),"") -> 3 | G11: =IFERROR(INDEX('Raw Data'!$N$2:$N$251,MATCH($A11,'Raw Data'!$Y$2:$Y$251,0)),"") -> 2099.97 | H11: =IFERROR(INDEX('Raw Data'!$K$2:$K$251,MATCH($A11,'Raw Data'!$Y$2:$Y$251,0)),"") -> West
A12: 2 | B12: =IFERROR(INDEX('Raw Data'!$A$2:$A$251,MATCH($A12,'Raw Data'!$Y$2:$Y$251,0)),"") -> TRX0122 | C12: =IFERROR(INDEX('Raw Data'!$B$2:$B$251,MATCH($A12,'Raw Data'!$Y$2:$Y$251,0)),"") -> 45410 | D12: =IFERROR(INDEX('Raw Data'!$D$2:$D$251,MATCH($A12,'Raw Data'!$Y$2:$Y$251,0)),"") -> Mark Carter | E12: =IFERROR(INDEX('Raw Data'!$F$2:$F$251,MATCH($A12,'Raw Data'!$Y$2:$Y$251,0)),"") -> Laptop | F12: =IFERROR(INDEX('Raw Data'!$H$2:$H$251,MATCH($A12,'Raw Data'!$Y$2:$Y$251,0)),"") -> 4 | G12: =IFERROR(INDEX('Raw Data'!$N$2:$N$251,MATCH($A12,'Raw Data'!$Y$2:$Y$251,0)),"") -> 3599.96 | H12: =IFERROR(INDEX('Raw Data'!$K$2:$K$251,MATCH($A12,'Raw Data'!$Y$2:$Y$251,0)),"") -> West
A13: 3 | B13: =IFERROR(INDEX('Raw Data'!$A$2:$A$251,MATCH($A13,'Raw Data'!$Y$2:$Y$251,0)),"") -> TRX0231 | C13: =IFERROR(INDEX('Raw Data'!$B$2:$B$251,MATCH($A13,'Raw Data'!$Y$2:$Y$251,0)),"") -> 45412 | D13: =IFERROR(INDEX('Raw Data'!$D$2:$D$251,MATCH($A13,'Raw Data'!$Y$2:$Y$251,0)),"") -> Barbara Young | E13: =IFERROR(INDEX('Raw Data'!$F$2:$F$251,MATCH($A13,'Raw Data'!$Y$2:$Y$251,0)),"") -> Smartphone | F13: =IFERROR(INDEX('Raw Data'!$H$2:$H$251,MATCH($A13,'Raw Data'!$Y$2:$Y$251,0)),"") -> 5 | G13: =IFERROR(INDEX('Raw Data'!$N$2:$N$251,MATCH($A13,'Raw Data'!$Y$2:$Y$251,0)),"") -> 3499.95 | H13: =IFERROR(INDEX('Raw Data'!$K$2:$K$251,MATCH($A13,'Raw Data'!$Y$2:$Y$251,0)),"") -> West
A14: 4 | B14: =IFERROR(INDEX('Raw Data'!$A$2:$A$251,MATCH($A14,'Raw Data'!$Y$2:$Y$251,0)),"") -> TRX0242 | C14: =IFERROR(INDEX('Raw Data'!$B$2:$B$251,MATCH($A14,'Raw Data'!$Y$2:$Y$251,0)),"") -> 45416 | D14: =IFERROR(INDEX('Raw Data'!$D$2:$D$251,MATCH($A14,'Raw Data'!$Y$2:$Y$251,0)),"") -> Mark Carter | E14: =IFERROR(INDEX('Raw Data'!$F$2:$F$251,MATCH($A14,'Raw Data'!$Y$2:$Y$251,0)),"") -> Desk | F14: =IFERROR(INDEX('Raw Data'!$H$2:$H$251,MATCH($A14,'Raw Data'!$Y$2:$Y$251,0)),"") -> 4 | G14: =IFERROR(INDEX('Raw Data'!$N$2:$N$251,MATCH($A14,'Raw Data'!$Y$2:$Y$251,0)),"") -> 1199.96 | H14: =IFERROR(INDEX('Raw Data'!$K$2:$K$251,MATCH($A14,'Raw Data'!$Y$2:$Y$251,0)),"") -> West
A15: 5 | B15: =IFERROR(INDEX('Raw Data'!$A$2:$A$251,MATCH($A15,'Raw Data'!$Y$2:$Y$251,0)),"") -> TRX0071 | C15: =IFERROR(INDEX('Raw Data'!$B$2:$B$251,MATCH($A15,'Raw Data'!$Y$2:$Y$251,0)),"") -> 45422 | D15: =IFERROR(INDEX('Raw Data'!$D$2:$D$251,MATCH($A15,'Raw Data'!$Y$2:$Y$251,0)),"") -> Nancy Collins | E15: =IFERROR(INDEX('Raw Data'!$F$2:$F$251,MATCH($A15,'Raw Data'!$Y$2:$Y$251,0)),"") -> Monitor | F15: =IFERROR(INDEX('Raw Data'!$H$2:$H$251,MATCH($A15,'Raw Data'!$Y$2:$Y$251,0)),"") -> 5 | G15: =IFERROR(INDEX('Raw Data'!$N$2:$N$251,MATCH($A15,'Raw Data'!$Y$2:$Y$251,0)),"") -> 1249.95 | H15: =IFERROR(INDEX('Raw Data'!$K$2:$K$251,MATCH($A15,'Raw Data'!$Y$2:$Y$251,0)),"") -> West
A16: 6 | B16: =IFERROR(INDEX('Raw Data'!$A$2:$A$251,MATCH($A16,'Raw Data'!$Y$2:$Y$251,0)),"") -> TRX0015 | C16: =IFERROR(INDEX('Raw Data'!$B$2:$B$251,MATCH($A16,'Raw Data'!$Y$2:$Y$251,0)),"") -> 45440 | D16: =IFERROR(INDEX('Raw Data'!$D$2:$D$251,MATCH($A16,'Raw Data'!$Y$2:$Y$251,0)),"") -> Jennifer Taylor | E16: =IFERROR(INDEX('Raw Data'!$F$2:$F$251,MATCH($A16,'Raw Data'!$Y$2:$Y$251,0)),"") -> Smartphone | F16: =IFERROR(INDEX('Raw Data'!$H$2:$H$251,MATCH($A16,'Raw Data'!$Y$2:$Y$251,0)),"") -> 5 | G16: =IFERROR(INDEX('Raw Data'!$N$2:$N$251,MATCH($A16,'Raw Data'!$Y$2:$Y$251,0)),"") -> 3499.95 | H16: =IFERROR(INDEX('Raw Data'!$K$2:$K$251,MATCH($A16,'Raw Data'!$Y$2:$Y$251,0)),"") -> West
A17: 7 | B17: =IFERROR(INDEX('Raw Data'!$A$2:$A$251,MATCH($A17,'Raw Data'!$Y$2:$Y$251,0)),"") -> TRX0158 | C17: =IFERROR(INDEX('Raw Data'!$B$2:$B$251,MATCH($A17,'Raw Data'!$Y$2:$Y$251,0)),"") -> 45579 | D17: =IFERROR(INDEX('Raw Data'!$D$2:$D$251,MATCH($A17,'Raw Data'!$Y$2:$Y$251,0)),"") -> George Adams | E17: =IFERROR(INDEX('Raw Data'!$F$2:$F$251,MATCH($A17,'Raw Data'!$Y$2:$Y$251,0)),"") -> Laptop | F17: =IFERROR(INDEX('Raw Data'!$H$2:$H$251,MATCH($A17,'Raw Data'!$Y$2:$Y$251,0)),"") -> 3 | G17: =IFERROR(INDEX('Raw Data'!$N$2:$N$251,MATCH($A17,'Raw Data'!$Y$2:$Y$251,0)),"") -> 2699.97 | H17: =IFERROR(INDEX('Raw Data'!$K$2:$K$251,MATCH($A17,'Raw Data'!$Y$2:$Y$251,0)),"") -> West
A18: 8 | B18: =IFERROR(INDEX('Raw Data'!$A$2:$A$251,MATCH($A18,'Raw Data'!$Y$2:$Y$251,0)),"") -> TRX0033 | C18: =IFERROR(INDEX('Raw Data'!$B$2:$B$251,MATCH($A18,'Raw Data'!$Y$2:$Y$251,0)),"") -> 45613 | D18: =IFERROR(INDEX('Raw Data'!$D$2:$D$251,MATCH($A18,'Raw Data'!$Y$2:$Y$251,0)),"") -> Mark Carter | E18: =IFERROR(INDEX('Raw Data'!$F$2:$F$251,MATCH($A18,'Raw Data'!$Y$2:$Y$251,0)),"") -> Smartphone | F18: =IFERROR(INDEX('Raw Data'!$H$2:$H$251,MATCH($A18,'Raw Data'!$Y$2:$Y$251,0)),"") -> 2 | G18: =IFERROR(INDEX('Raw Data'!$N$2:$N$251,MATCH($A18,'Raw Data'!$Y$2:$Y$251,0)),"") -> 1399.98 | H18: =IFERROR(INDEX('Raw Data'!$K$2:$K$251,MATCH($A18,'Raw Data'!$Y$2:$Y$251,0)),"") -> West
A19: 9 | B19: =IFERROR(INDEX('Raw Data'!$A$2:$A$251,MATCH($A19,'Raw Data'!$Y$2:$Y$251,0)),"") -> TRX0148 | C19: =IFERROR(INDEX('Raw Data'!$B$2:$B$251,MATCH($A19,'Raw Data'!$Y$2:$Y$251,0)),"") -> 45619 | D19: =IFERROR(INDEX('Raw Data'!$D$2:$D$251,MATCH($A19,'Raw Data'!$Y$2:$Y$251,0)),"") -> Sarah Davis | E19: =IFERROR(INDEX('Raw Data'!$F$2:$F$251,MATCH($A19,'Raw Data'!$Y$2:$Y$251,0)),"") -> Smartphone | F19: =IFERROR(INDEX('Raw Data'!$H$2:$H$251,MATCH($A19,'Raw Data'!$Y$2:$Y$251,0)),"") -> 3 | G19: =IFERROR(INDEX('Raw Data'!$N$2:$N$251,MATCH($A19,'Raw Data'!$Y$2:$Y$251,0)),"") -> 2099.97 | H19: =IFERROR(INDEX('Raw Data'!$K$2:$K$251,MATCH($A19,'Raw Data'!$Y$2:$Y$251,0)),"") -> West
A20: 10 | B20: =IFERROR(INDEX('Raw Data'!$A$2:$A$251,MATCH($A20,'Raw Data'!$Y$2:$Y$251,0)),"") -> TRX0201 | C20: =IFERROR(INDEX('Raw Data'!$B$2:$B$251,MATCH($A20,'Raw Data'!$Y$2:$Y$251,0)),"") -> 45627 | D20: =IFERROR(INDEX('Raw Data'!$D$2:$D$251,MATCH($A20,'Raw Data'!$Y$2:$Y$251,0)),"") -> Mark Carter | E20: =IFERROR(INDEX('Raw Data'!$F$2:$F$251,MATCH($A20,'Raw Data'!$Y$2:$Y$251,0)),"") -> Smartphone | F20: =IFERROR(INDEX('Raw Data'!$H$2:$H$251,MATCH($A20,'Raw Data'!$Y$2:$Y$251,0)),"") -> 5 | G20: =IFERROR(INDEX('Raw Data'!$N$2:$N$251,MATCH($A20,'Raw Data'!$Y$2:$Y$251,0)),"") -> 3499.95 | H20: =IFERROR(INDEX('Raw Data'!$K$2:$K$251,MATCH($A20,'Raw Data'!$Y$2:$Y$251,0)),"") -> West
A21: 11 | B21: =IFERROR(INDEX('Raw Data'!$A$2:$A$251,MATCH($A21,'Raw Data'!$Y$2:$Y$251,0)),"") -> TRX0010 | C21: =IFERROR(INDEX('Raw Data'!$B$2:$B$251,MATCH($A21,'Raw Data'!$Y$2:$Y$251,0)),"") -> 45688 | D21: =IFERROR(INDEX('Raw Data'!$D$2:$D$251,MATCH($A21,'Raw Data'!$Y$2:$Y$251,0)),"") -> Karen Hill | E21: =IFERROR(INDEX('Raw Data'!$F$2:$F$251,MATCH($A21,'Raw Data'!$Y$2:$Y$251,0)),"") -> Smartphone | F21: =IFERROR(INDEX('Raw Data'!$H$2:$H$251,MATCH($A21,'Raw Data'!$Y$2:$Y$251,0)),"") -> 4 | G21: =IFERROR(INDEX('Raw Data'!$N$2:$N$251,MATCH($A21,'Raw Data'!$Y$2:$Y$251,0)),"") -> 2799.96 | H21: =IFERROR(INDEX('Raw Data'!$K$2:$K$251,MATCH($A21,'Raw Data'!$Y$2:$Y$251,0)),"") -> West
A22: 12 | B22: =IFERROR(INDEX('Raw Data'!$A$2:$A$251,MATCH($A22,'Raw Data'!$Y$2:$Y$251,0)),"") -> TRX0083 | C22: =IFERROR(INDEX('Raw Data'!$B$2:$B$251,MATCH($A22,'Raw Data'!$Y$2:$Y$251,0)),"") -> 45710 | D22: =IFERROR(INDEX('Raw Data'!$D$2:$D$251,MATCH($A22,'Raw Data'!$Y$2:$Y$251,0)),"") -> Charles Allen | E22: =IFERROR(INDEX('Raw Data'!$F$2:$F$251,MATCH($A22,'Raw Data'!$Y$2:$Y$251,0)),"") -> Desk | F22: =IFERROR(INDEX('Raw Data'!$H$2:$H$251,MATCH($A22,'Raw Data'!$Y$2:$Y$251,0)),"") -> 5 | G22: =IFERROR(INDEX('Raw Data'!$N$2:$N$251,MATCH($A22,'Raw Data'!$Y$2:$Y$251,0)),"") -> 1499.95 | H22: =IFERROR(INDEX('Raw Data'!$K$2:$K$251,MATCH($A22,'Raw Data'!$Y$2:$Y$251,0)),"") -> West
... A40: 30 | B40: =IFERROR(INDEX('Raw Data'!$A$2:$A$251,MATCH($A40,'Raw Data'!$Y$2:$Y$251,0)),"") | C40: =IFERROR(INDEX('Raw Data'!$B$2:$B$251,MATCH($A40,'Raw Data'!$Y$2:$Y$251,0)),"") | D40: =IFERROR(INDEX('Raw Data'!$D$2:$D$251,MATCH($A40,'Raw Data'!$Y$2:$Y$251,0)),"") | E40: =IFERROR(INDEX('Raw Data'!$F$2:$F$251,MATCH($A40,'Raw Data'!$Y$2:$Y$251,0)),"") | F40: =IFERROR(INDEX('Raw Data'!$H$2:$H$251,MATCH($A40,'Raw Data'!$Y$2:$Y$251,0)),"") | G40: =IFERROR(INDEX('Raw Data'!$N$2:$N$251,MATCH($A40,'Raw Data'!$Y$2:$Y$251,0)),"") | H40: =IFERROR(INDEX('Raw Data'!$K$2:$K$251,MATCH($A40,'Raw Data'!$Y$2:$Y$251,0)),"")

Sheet Pivots
A1: Pivot Tables
A2: Seven live PivotTables built on the Raw Data table (A1:Z251). Use the report filters (▼) above each table; right-click any table > Refresh after editing data.
A3: To add Slicers/Timeline: click a pivot > PivotTable Analyze > Insert Slicer (Region, Category, Customer_Segment, Payment_Method) > Insert Timeline (Date), then Report Connections > tick all pivots.
A4: Revenue by Region | E4: Revenue by Month | I4: Revenue by Category | M4: Revenue by Product | Q4: Orders by Payment Method | U4: Revenue by Customer (GroupBy) | Y4: Region x Category crosstab
A6: Filter | E6: Filter | I6: Filter | M6: Filter | Q6: Filter | U6: Filter | Y6: Filter
A7: Category | B7: - all - | E7: Region | F7: - all - | I7: Region | J7: - all - | M7: Region | N7: - all - | Q7: Region | R7: - all - | U7: Region | V7: - all - | Y7: Payment_Method | Z7: - all -
A8: Payment_Method | B8: - all - | E8: Category | F8: - all - | I8: Payment_Method | J8: - all - | M8: Category | N8: - all - | Q8: Category | R8: - all - | U8: Category | V8: - all -
Y9: Revenue ($) | Z9: Category
A10: Region | B10: Revenue ($) | E10: Year_Month | F10: Revenue ($) | I10: Category | J10: Revenue ($) | M10: Product_Name | N10: Revenue ($) | Q10: Payment_Method | R10: Orders | U10: Customer_Name | V10: Revenue ($) | Y10: Region | Z10: Appliances | AA10: Electronics | AB10: Furniture | AC10: Grand Total
A11: Central | B11: 41288.34 | E11: 2024-04 | F11: 20919.33 | I11: Appliances | J11: 8338.74 | M11: Blender | N11: 5219.13 | Q11: Cash | R11: 76 | U11: Arthur Edwards | V11: 1559.94 | Y11: Central | Z11: 1999.71 | AA11: 24889.33 | AB11: 14399.3 | AC11: 41288.34
A12: East | B12: 59288.39 | E12: 2024-05 | F12: 17039.35 | I12: Electronics | J12: 171756.05 | M12: Bookshelf | N12: 15298.98 | Q12: Credit Card | R12: 68 | U12: Barbara Young | V12: 10649.8 | Y12: East | Z12: 2239.67 | AA12: 50649.01 | AB12: 6399.71 | AC12: 59288.39
A13: North | B13: 50808.31 | E13: 2024-06 | F13: 19299.45 | I13: Furniture | J13: 49097.68 | M13: Coffee Maker | N13: 3119.61 | Q13: Debit Card | R13: 54 | U13: Betty Campbell | V13: 5649.84 | Y13: North | Z13: 1119.84 | AA13: 39239.04 | AB13: 10449.43 | AC13: 50808.31
A14: South | B14: 36398.75 | E14: 2024-07 | F14: 18479.4 | I14: Grand Total | J14: 229192.47 | M14: Desk | N14: 23399.22 | Q14: PayPal | R14: 52 | U14: Carol Evans | V14: 1149.93 | Y14: South | Z14: 1099.83 | AA14: 25549.32 | AB14: 9749.6 | AC14: 36398.75
A15: West | B15: 41408.68 | E15: 2024-08 | F15: 15759.43 | M15: Headphones | N15: 7049.53 | Q15: Grand Total | R15: 250 | U15: Charles Allen | V15: 5089.73 | Y15: West | Z15: 1879.69 | AA15: 31429.35 | AB15: 8099.64 | AC15: 41408.68
A16: Grand Total | B16: 229192.47 | E16: 2024-09 | F16: 12989.51 | M16: Keyboard | N16: 8009.11 | U16: Cynthia Price | V16: 3769.83 | Y16: Grand Total | Z16: 8338.74 | AA16: 171756.05 | AB16: 49097.68 | AC16: 229192.47
E17: 2024-10 | F17: 20609.52 | M17: Laptop | N17: 67499.25 | U17: Daniel King | V17: 7309.8
E18: 2024-11 | F18: 12309.44 | M18: Monitor | N18: 21999.12 | U18: David Martinez | V18: 1809.84
E19: 2024-12 | F19: 23039.3 | M19: Office Chair | N19: 10399.48 | U19: Dennis Gray | V19: 479.92
E20: 2025-01 | F20: 25799.15 | M20: Smartphone | N20: 67199.04 | U20: Dorothy Nelson | V20: 8269.79
E21: 2025-02 | F21: 16069.38 | M21: Grand Total | N21: 229192.47 | U21: Douglas Watson | V21: 4829.89
E22: 2025-03 | F22: 19899.38 | U22: Edward Mitchell | V22: 11919.77
E23: 2025-04 | F23: 6979.83 | U23: Elizabeth Hall | V23: 3649.86
E24: Grand Total | F24: 229192.47 | U24: Emma Wilson | V24: 1229.88
U25: Frank Torres | V25: 1479.91
U26: George Adams | V26: 3779.93
U27: Gerald Murphy | V27: 6379.87
U28: Harry Morgan | V28: 5519.89
U29: Helen Roberts | V29: 6459.79
U30: James Johnson | V30: 179.97
U31: Jennifer Taylor | V31: 4739.85
U32: John Smith | V32: 599.96
U33: Joseph Jackson | V33: 6949.84
U34: Julie Foster | V34: 239.96
U35: Karen Hill | V35: 8009.77
U36: Kathleen Bennett | V36: 4309.81
... U61: Grand Total | V61: 229192.47

Sheet Regression Output
A1: SUMMARY OUTPUT: Regression (Y = Monthly Revenue, X = Month Index)
A3: Regression Statistics
A4: Multiple R | B4: =ABS(CORREL(Analysis!$E$90:$E$101,Analysis!$C$90:$C$101)) -> 0.1458533
A5: R Square | B5: =RSQ(Analysis!$E$90:$E$101,Analysis!$C$90:$C$101) -> 0.021273185
A6: Adjusted R Square | B6: =1-(1-B5)*(B8-1)/(B8-2) -> -0.076599496
A7: Standard Error | B7: =STEYX(Analysis!$E$90:$E$101,Analysis!$C$90:$C$101) -> 4091.2421
A8: Observations | B8: =COUNT(Analysis!$E$90:$E$101) -> 12
A10: ANOVA
B11: df | C11: SS | D11: MS | E11: F | F11: Significance F
A12: Regression | B12: 1 | C12: =INDEX(LINEST(Analysis!$E$90:$E$101,Analysis!$C$90:$C$101,TRUE(),TRUE()),5,1) -> 3638156.7 | D12: =C12/B12 -> 3638156.7 | E12: =D12/D13 -> 0.2173557 | F12: =FDIST(E12,B12,B13) -> 0.65105213
A13: Residual | B13: =B8-2 -> 10 | C13: =INDEX(LINEST(Analysis!$E$90:$E$101,Analysis!$C$90:$C$101,TRUE(),TRUE()),5,2) -> 1.6738262e+08 | D13: =C13/B13 -> 16738262
A14: Total | B14: =B8-1 -> 11 | C14: =C12+C13 -> 1.7102078e+08
A16: Coefficients
B17: Coefficients | C17: Standard Error | D17: t Stat | E17: P-value | F17: Lower 95% | G17: Upper 95%
A18: Intercept | B18: =INDEX(LINEST(Analysis!$E$90:$E$101,Analysis!$C$90:$C$101,TRUE(),TRUE()),1,2) -> 17480.941 | C18: =INDEX(LINEST(Analysis!$E$90:$E$101,Analysis!$C$90:$C$101,TRUE(),TRUE()),2,2) -> 2517.9855 | D18: =B18/C18 -> 6.9424314 | E18: =TDIST(ABS(D18),$B$13,2) -> 3.9835382e-05 | F18: =B18-TINV(0.05,$B$13)*C18 -> 11870.52 | G18: =B18+TINV(0.05,$B$13)*C18 -> 23091.363
A19: X Variable 1 (Month Index) | B19: =INDEX(LINEST(Analysis!$E$90:$E$101,Analysis!$C$90:$C$101,TRUE(),TRUE()),1,1) -> 159.50441 | C19: =INDEX(LINEST(Analysis!$E$90:$E$101,Analysis!$C$90:$C$101,TRUE(),TRUE()),2,1) -> 342.12685 | D19: =B19/C19 -> 0.46621422 | E19: =TDIST(ABS(D19),$B$13,2) -> 0.65105213 | F19: =B19-TINV(0.05,$B$13)*C19 -> -602.80173 | G19: =B19+TINV(0.05,$B$13)*C19 -> 921.81054
A21: RESIDUAL OUTPUT
A22: Observation | B22: Month | C22: Predicted Revenue | D22: Residuals
A23: 1 | B23: =Analysis!B90 -> Apr-24 | C23: =$B$18+$B$19*Analysis!C90 -> 17640.446 | D23: =Analysis!E90-C23 -> 3278.8842
A24: 2 | B24: =Analysis!B91 -> May-24 | C24: =$B$18+$B$19*Analysis!C91 -> 17799.95 | D24: =Analysis!E91-C24 -> -760.60017
A25: 3 | B25: =Analysis!B92 -> Jun-24 | C25: =$B$18+$B$19*Analysis!C92 -> 17959.455 | D25: =Analysis!E92-C25 -> 1339.9954
A26: 4 | B26: =Analysis!B93 -> Jul-24 | C26: =$B$18+$B$19*Analysis!C93 -> 18118.959 | D26: =Analysis!E93-C26 -> 360.44101
A27: 5 | B27: =Analysis!B94 -> Aug-24 | C27: =$B$18+$B$19*Analysis!C94 -> 18278.463 | D27: =Analysis!E94-C27 -> -2519.0334
A28: 6 | B28: =Analysis!B95 -> Sep-24 | C28: =$B$18+$B$19*Analysis!C95 -> 18437.968 | D28: =Analysis!E95-C28 -> -5448.4578
A29: 7 | B29: =Analysis!B96 -> Oct-24 | C29: =$B$18+$B$19*Analysis!C96 -> 18597.472 | D29: =Analysis!E96-C29 -> 2012.0478
A30: 8 | B30: =Analysis!B97 -> Nov-24 | C30: =$B$18+$B$19*Analysis!C97 -> 18756.977 | D30: =Analysis!E97-C30 -> -6447.5366
A31: 9 | B31: =Analysis!B98 -> Dec-24 | C31: =$B$18+$B$19*Analysis!C98 -> 18916.481 | D31: =Analysis!E98-C31 -> 4122.819
A32: 10 | B32: =Analysis!B99 -> Jan-25 | C32: =$B$18+$B$19*Analysis!C99 -> 19075.985 | D32: =Analysis!E99-C32 -> 6723.1646
A33: 11 | B33: =Analysis!B100 -> Feb-25 | C33: =$B$18+$B$19*Analysis!C100 -> 19235.49 | D33: =Analysis!E100-C33 -> -3166.1098
A34: 12 | B34: =Analysis!B101 -> Mar-25 | C34: =$B$18+$B$19*Analysis!C101 -> 19394.994 | D34: =Analysis!E101-C34 -> 504.38577

Sheet Scenario Summary
A1: Scenario Summary
B4: Current Values | C4: Base case | D4: Optimistic | E4: Pessimistic
A5: Changing Cells:
A6: Price change % | B6: =Analysis!B120 -> 0 | C6: =Analysis!C120 -> 0 | D6: =Analysis!D120 -> 0.05 | E6: =Analysis!E120 -> -0.03
A7: Volume change % | B7: =Analysis!B121 -> 0 | C7: =Analysis!C121 -> 0 | D7: =Analysis!D121 -> 0.1 | E7: =Analysis!E121 -> -0.08
A8: Discount % | B8: =Analysis!B122 -> 0 | C8: =Analysis!C122 -> 0 | D8: =Analysis!D122 -> 0 | E8: =Analysis!E122 -> 0.05
A9: Result Cells:
A10: Projected revenue | B10: =Analysis!B124 -> 229192.47 | C10: =Analysis!C124 -> 229192.47 | D10: =Analysis!D124 -> 264717.3 | E10: =Analysis!E124 -> 194304.79
A11: Change vs baseline | B11: =Analysis!B125 -> 0 | C11: =Analysis!C125 -> 0 | D11: =Analysis!D125 -> 0.155 | E11: =Analysis!E125 -> -0.15222
A14: Goal Seek result
A15: Target revenue uplift | B15: =Analysis!B127 -> 0.2
A16: Target revenue | B16: =Analysis!B128 -> 275030.96
A17: Price change that reaches target (Goal Seek: set Projected revenue to target by changing price change) | B17: =Analysis!B129 -> 0.2
A18: Projected revenue at that price | B18: =Analysis!B123*(1+B17)*(1+Analysis!B121)*(1-Analysis!B122) -> 275030.96
A19: Difference to target (0 = solved) | B19: =ROUND(B18-B16,2) -> 0

Sheet Visualizations
A1: Visualizations
A2: Charts linked to the Analysis tables. Pivot charts and the interactive filtered charts are on the Dashboard.
A4: Revenue by Region | J4: Monthly Revenue Trend
A21: Revenue Share by Category | J21: Revenue by Product
A38: Orders by Payment Method

Sheet Calc
A2: Regions | B2: Categories | C2: Payment | D2: Segments
A3: All | B3: All | C3: All | D3: All
A4: Central | B4: Appliances | C4: Cash | D4: Basic
A5: East | B5: Electronics | C5: Credit Card | D5: Premium
A6: North | B6: Furniture | C6: Debit Card | D6: Standard
A7: South | C7: PayPal
A8: West
A9: Criteria (wildcard * = All)
A10: Region | B10: =IF(Dashboard!$B$11="All","*",Dashboard!$B$11) -> *
A11: Category | B11: =IF(Dashboard!$E$11="All","*",Dashboard!$E$11) -> *
A12: Payment | B12: =IF(Dashboard!$H$11="All","*",Dashboard!$H$11) -> *
A13: Segment | B13: =IF(Dashboard!$K$11="All","*",Dashboard!$K$11) -> *
A14: From date | B14: =Dashboard!$N$11 -> 45383
A15: To date | B15: =Dashboard!$Q$11 -> 45777
A19: Month | B19: Month_End | C19: Revenue | D19: Orders
A20: =Analysis!B90 -> Apr-24 | B20: =Analysis!A90 -> 45412 | C20: =SUMIFS('Raw Data'!$N$2:$N$251,'Raw Data'!$K$2:$K$251,$B$10,'Raw Data'!$G$2:$G$251,$B$11,'Raw Data'!$J$2:$J$251,$B$12,'Raw Data'!$L$2:$L$251,$B$13,'Raw Data'!$B$2:$B$251,">="&$B$14,'Raw Data'!$B$2:$B$251,"<="&$B$15,'Raw Data'!$P$2:$P$251,B20) -> 20919.33 | D20: =COUNTIFS('Raw Data'!$K$2:$K$251,$B$10,'Raw Data'!$G$2:$G$251,$B$11,'Raw Data'!$J$2:$J$251,$B$12,'Raw Data'!$L$2:$L$251,$B$13,'Raw Data'!$B$2:$B$251,">="&$B$14,'Raw Data'!$B$2:$B$251,"<="&$B$15,'Raw Data'!$P$2:$P$251,B20) -> 21
A21: =Analysis!B91 -> May-24 | B21: =Analysis!A91 -> 45443 | C21: =SUMIFS('Raw Data'!$N$2:$N$251,'Raw Data'!$K$2:$K$251,$B$10,'Raw Data'!$G$2:$G$251,$B$11,'Raw Data'!$J$2:$J$251,$B$12,'Raw Data'!$L$2:$L$251,$B$13,'Raw Data'!$B$2:$B$251,">="&$B$14,'Raw Data'!$B$2:$B$251,"<="&$B$15,'Raw Data'!$P$2:$P$251,B21) -> 17039.35 | D21: =COUNTIFS('Raw Data'!$K$2:$K$251,$B$10,'Raw Data'!$G$2:$G$251,$B$11,'Raw Data'!$J$2:$J$251,$B$12,'Raw Data'!$L$2:$L$251,$B$13,'Raw Data'!$B$2:$B$251,">="&$B$14,'Raw Data'!$B$2:$B$251,"<="&$B$15,'Raw Data'!$P$2:$P$251,B21) -> 19
A22: =Analysis!B92 -> Jun-24 | B22: =Analysis!A92 -> 45473 | C22: =SUMIFS('Raw Data'!$N$2:$N$251,'Raw Data'!$K$2:$K$251,$B$10,'Raw Data'!$G$2:$G$251,$B$11,'Raw Data'!$J$2:$J$251,$B$12,'Raw Data'!$L$2:$L$251,$B$13,'Raw Data'!$B$2:$B$251,">="&$B$14,'Raw Data'!$B$2:$B$251,"<="&$B$15,'Raw Data'!$P$2:$P$251,B22) -> 19299.45 | D22: =COUNTIFS('Raw Data'!$K$2:$K$251,$B$10,'Raw Data'!$G$2:$G$251,$B$11,'Raw Data'!$J$2:$J$251,$B$12,'Raw Data'!$L$2:$L$251,$B$13,'Raw Data'!$B$2:$B$251,">="&$B$14,'Raw Data'!$B$2:$B$251,"<="&$B$15,'Raw Data'!$P$2:$P$251,B22) -> 19
A23: =Analysis!B93 -> Jul-24 | B23: =Analysis!A93 -> 45504 | C23: =SUMIFS('Raw Data'!$N$2:$N$251,'Raw Data'!$K$2:$K$251,$B$10,'Raw Data'!$G$2:$G$251,$B$11,'Raw Data'!$J$2:$J$251,$B$12,'Raw Data'!$L$2:$L$251,$B$13,'Raw Data'!$B$2:$B$251,">="&$B$14,'Raw Data'!$B$2:$B$251,"<="&$B$15,'Raw Data'!$P$2:$P$251,B23) -> 18479.4 | D23: =COUNTIFS('Raw Data'!$K$2:$K$251,$B$10,'Raw Data'!$G$2:$G$251,$B$11,'Raw Data'!$J$2:$J$251,$B$12,'Raw Data'!$L$2:$L$251,$B$13,'Raw Data'!$B$2:$B$251,">="&$B$14,'Raw Data'!$B$2:$B$251,"<="&$B$15,'Raw Data'!$P$2:$P$251,B23) -> 24
A24: =Analysis!B94 -> Aug-24 | B24: =Analysis!A94 -> 45535 | C24: =SUMIFS('Raw Data'!$N$2:$N$251,'Raw Data'!$K$2:$K$251,$B$10,'Raw Data'!$G$2:$G$251,$B$11,'Raw Data'!$J$2:$J$251,$B$12,'Raw Data'!$L$2:$L$251,$B$13,'Raw Data'!$B$2:$B$251,">="&$B$14,'Raw Data'!$B$2:$B$251,"<="&$B$15,'Raw Data'!$P$2:$P$251,B24) -> 15759.43 | D24: =COUNTIFS('Raw Data'!$K$2:$K$251,$B$10,'Raw Data'!$G$2:$G$251,$B$11,'Raw Data'!$J$2:$J$251,$B$12,'Raw Data'!$L$2:$L$251,$B$13,'Raw Data'!$B$2:$B$251,">="&$B$14,'Raw Data'!$B$2:$B$251,"<="&$B$15,'Raw Data'!$P$2:$P$251,B24) -> 18
A25: =Analysis!B95 -> Sep-24 | B25: =Analysis!A95 -> 45565 | C25: =SUMIFS('Raw Data'!$N$2:$N$251,'Raw Data'!$K$2:$K$251,$B$10,'Raw Data'!$G$2:$G$251,$B$11,'Raw Data'!$J$2:$J$251,$B$12,'Raw Data'!$L$2:$L$251,$B$13,'Raw Data'!$B$2:$B$251,">="&$B$14,'Raw Data'!$B$2:$B$251,"<="&$B$15,'Raw Data'!$P$2:$P$251,B25) -> 12989.51 | D25: =COUNTIFS('Raw Data'!$K$2:$K$251,$B$10,'Raw Data'!$G$2:$G$251,$B$11,'Raw Data'!$J$2:$J$251,$B$12,'Raw Data'!$L$2:$L$251,$B$13,'Raw Data'!$B$2:$B$251,">="&$B$14,'Raw Data'!$B$2:$B$251,"<="&$B$15,'Raw Data'!$P$2:$P$251,B25) -> 19
A26: =Analysis!B96 -> Oct-24 | B26: =Analysis!A96 -> 45596 | C26: =SUMIFS('Raw Data'!$N$2:$N$251,'Raw Data'!$K$2:$K$251,$B$10,'Raw Data'!$G$2:$G$251,$B$11,'Raw Data'!$J$2:$J$251,$B$12,'Raw Data'!$L$2:$L$251,$B$13,'Raw Data'!$B$2:$B$251,">="&$B$14,'Raw Data'!$B$2:$B$251,"<="&$B$15,'Raw Data'!$P$2:$P$251,B26) -> 20609.52 | D26: =COUNTIFS('Raw Data'!$K$2:$K$251,$B$10,'Raw Data'!$G$2:$G$251,$B$11,'Raw Data'!$J$2:$J$251,$B$12,'Raw Data'!$L$2:$L$251,$B$13,'Raw Data'!$B$2:$B$251,">="&$B$14,'Raw Data'!$B$2:$B$251,"<="&$B$15,'Raw Data'!$P$2:$P$251,B26) -> 16
A27: =Analysis!B97 -> Nov-24 | B27: =Analysis!A97 -> 45626 | C27: =SUMIFS('Raw Data'!$N$2:$N$251,'Raw Data'!$K$2:$K$251,$B$10,'Raw Data'!$G$2:$G$251,$B$11,'Raw Data'!$J$2:$J$251,$B$12,'Raw Data'!$L$2:$L$251,$B$13,'Raw Data'!$B$2:$B$251,">="&$B$14,'Raw Data'!$B$2:$B$251,"<="&$B$15,'Raw Data'!$P$2:$P$251,B27) -> 12309.44 | D27: =COUNTIFS('Raw Data'!$K$2:$K$251,$B$10,'Raw Data'!$G$2:$G$251,$B$11,'Raw Data'!$J$2:$J$251,$B$12,'Raw Data'!$L$2:$L$251,$B$13,'Raw Data'!$B$2:$B$251,">="&$B$14,'Raw Data'!$B$2:$B$251,"<="&$B$15,'Raw Data'!$P$2:$P$251,B27) -> 17
A28: =Analysis!B98 -> Dec-24 | B28: =Analysis!A98 -> 45657 | C28: =SUMIFS('Raw Data'!$N$2:$N$251,'Raw Data'!$K$2:$K$251,$B$10,'Raw Data'!$G$2:$G$251,$B$11,'Raw Data'!$J$2:$J$251,$B$12,'Raw Data'!$L$2:$L$251,$B$13,'Raw Data'!$B$2:$B$251,">="&$B$14,'Raw Data'!$B$2:$B$251,"<="&$B$15,'Raw Data'!$P$2:$P$251,B28) -> 23039.3 | D28: =COUNTIFS('Raw Data'!$K$2:$K$251,$B$10,'Raw Data'!$G$2:$G$251,$B$11,'Raw Data'!$J$2:$J$251,$B$12,'Raw Data'!$L$2:$L$251,$B$13,'Raw Data'!$B$2:$B$251,">="&$B$14,'Raw Data'!$B$2:$B$251,"<="&$B$15,'Raw Data'!$P$2:$P$251,B28) -> 25
A29: =Analysis!B99 -> Jan-25 | B29: =Analysis!A99 -> 45688 | C29: =SUMIFS('Raw Data'!$N$2:$N$251,'Raw Data'!$K$2:$K$251,$B$10,'Raw Data'!$G$2:$G$251,$B$11,'Raw Data'!$J$2:$J$251,$B$12,'Raw Data'!$L$2:$L$251,$B$13,'Raw Data'!$B$2:$B$251,">="&$B$14,'Raw Data'!$B$2:$B$251,"<="&$B$15,'Raw Data'!$P$2:$P$251,B29) -> 25799.15 | D29: =COUNTIFS('Raw Data'!$K$2:$K$251,$B$10,'Raw Data'!$G$2:$G$251,$B$11,'Raw Data'!$J$2:$J$251,$B$12,'Raw Data'!$L$2:$L$251,$B$13,'Raw Data'!$B$2:$B$251,">="&$B$14,'Raw Data'!$B$2:$B$251,"<="&$B$15,'Raw Data'!$P$2:$P$251,B29) -> 26
A30: =Analysis!B100 -> Feb-25 | B30: =Analysis!A100 -> 45716 | C30: =SUMIFS('Raw Data'!$N$2:$N$251,'Raw Data'!$K$2:$K$251,$B$10,'Raw Data'!$G$2:$G$251,$B$11,'Raw Data'!$J$2:$J$251,$B$12,'Raw Data'!$L$2:$L$251,$B$13,'Raw Data'!$B$2:$B$251,">="&$B$14,'Raw Data'!$B$2:$B$251,"<="&$B$15,'Raw Data'!$P$2:$P$251,B30) -> 16069.38 | D30: =COUNTIFS('Raw Data'!$K$2:$K$251,$B$10,'Raw Data'!$G$2:$G$251,$B$11,'Raw Data'!$J$2:$J$251,$B$12,'Raw Data'!$L$2:$L$251,$B$13,'Raw Data'!$B$2:$B$251,">="&$B$14,'Raw Data'!$B$2:$B$251,"<="&$B$15,'Raw Data'!$P$2:$P$251,B30) -> 20
A31: =Analysis!B101 -> Mar-25 | B31: =Analysis!A101 -> 45747 | C31: =SUMIFS('Raw Data'!$N$2:$N$251,'Raw Data'!$K$2:$K$251,$B$10,'Raw Data'!$G$2:$G$251,$B$11,'Raw Data'!$J$2:$J$251,$B$12,'Raw Data'!$L$2:$L$251,$B$13,'Raw Data'!$B$2:$B$251,">="&$B$14,'Raw Data'!$B$2:$B$251,"<="&$B$15,'Raw Data'!$P$2:$P$251,B31) -> 19899.38 | D31: =COUNTIFS('Raw Data'!$K$2:$K$251,$B$10,'Raw Data'!$G$2:$G$251,$B$11,'Raw Data'!$J$2:$J$251,$B$12,'Raw Data'!$L$2:$L$251,$B$13,'Raw Data'!$B$2:$B$251,">="&$B$14,'Raw Data'!$B$2:$B$251,"<="&$B$15,'Raw Data'!$P$2:$P$251,B31) -> 19
A32: =Analysis!B102 -> Apr-25 | B32: =Analysis!A102 -> 45777 | C32: =SUMIFS('Raw Data'!$N$2:$N$251,'Raw Data'!$K$2:$K$251,$B$10,'Raw Data'!$G$2:$G$251,$B$11,'Raw Data'!$J$2:$J$251,$B$12,'Raw Data'!$L$2:$L$251,$B$13,'Raw Data'!$B$2:$B$251,">="&$B$14,'Raw Data'!$B$2:$B$251,"<="&$B$15,'Raw Data'!$P$2:$P$251,B32) -> 6979.83 | D32: =COUNTIFS('Raw Data'!$K$2:$K$251,$B$10,'Raw Data'!$G$2:$G$251,$B$11,'Raw Data'!$J$2:$J$251,$B$12,'Raw Data'!$L$2:$L$251,$B$13,'Raw Data'!$B$2:$B$251,">="&$B$14,'Raw Data'!$B$2:$B$251,"<="&$B$15,'Raw Data'!$P$2:$P$251,B32) -> 7
A35: Region | B35: Revenue | C35: Orders
A36: Central | B36: =SUMIFS('Raw Data'!$N$2:$N$251,'Raw Data'!$K$2:$K$251,$B$10,'Raw Data'!$G$2:$G$251,$B$11,'Raw Data'!$J$2:$J$251,$B$12,'Raw Data'!$L$2:$L$251,$B$13,'Raw Data'!$B$2:$B$251,">="&$B$14,'Raw Data'!$B$2:$B$251,"<="&$B$15,'Raw Data'!$K$2:$K$251,A36) -> 41288.34 | C36: =COUNTIFS('Raw Data'!$K$2:$K$251,$B$10,'Raw Data'!$G$2:$G$251,$B$11,'Raw Data'!$J$2:$J$251,$B$12,'Raw Data'!$L$2:$L$251,$B$13,'Raw Data'!$B$2:$B$251,">="&$B$14,'Raw Data'!$B$2:$B$251,"<="&$B$15,'Raw Data'!$K$2:$K$251,A36) -> 54
A37: East | B37: =SUMIFS('Raw Data'!$N$2:$N$251,'Raw Data'!$K$2:$K$251,$B$10,'Raw Data'!$G$2:$G$251,$B$11,'Raw Data'!$J$2:$J$251,$B$12,'Raw Data'!$L$2:$L$251,$B$13,'Raw Data'!$B$2:$B$251,">="&$B$14,'Raw Data'!$B$2:$B$251,"<="&$B$15,'Raw Data'!$K$2:$K$251,A37) -> 59288.39 | C37: =COUNTIFS('Raw Data'!$K$2:$K$251,$B$10,'Raw Data'!$G$2:$G$251,$B$11,'Raw Data'!$J$2:$J$251,$B$12,'Raw Data'!$L$2:$L$251,$B$13,'Raw Data'!$B$2:$B$251,">="&$B$14,'Raw Data'!$B$2:$B$251,"<="&$B$15,'Raw Data'!$K$2:$K$251,A37) -> 48
A38: North | B38: =SUMIFS('Raw Data'!$N$2:$N$251,'Raw Data'!$K$2:$K$251,$B$10,'Raw Data'!$G$2:$G$251,$B$11,'Raw Data'!$J$2:$J$251,$B$12,'Raw Data'!$L$2:$L$251,$B$13,'Raw Data'!$B$2:$B$251,">="&$B$14,'Raw Data'!$B$2:$B$251,"<="&$B$15,'Raw Data'!$K$2:$K$251,A38) -> 50808.31 | C38: =COUNTIFS('Raw Data'!$K$2:$K$251,$B$10,'Raw Data'!$G$2:$G$251,$B$11,'Raw Data'!$J$2:$J$251,$B$12,'Raw Data'!$L$2:$L$251,$B$13,'Raw Data'!$B$2:$B$251,">="&$B$14,'Raw Data'!$B$2:$B$251,"<="&$B$15,'Raw Data'!$K$2:$K$251,A38) -> 59
A39: South | B39: =SUMIFS('Raw Data'!$N$2:$N$251,'Raw Data'!$K$2:$K$251,$B$10,'Raw Data'!$G$2:$G$251,$B$11,'Raw Data'!$J$2:$J$251,$B$12,'Raw Data'!$L$2:$L$251,$B$13,'Raw Data'!$B$2:$B$251,">="&$B$14,'Raw Data'!$B$2:$B$251,"<="&$B$15,'Raw Data'!$K$2:$K$251,A39) -> 36398.75 | C39: =COUNTIFS('Raw Data'!$K$2:$K$251,$B$10,'Raw Data'!$G$2:$G$251,$B$11,'Raw Data'!$J$2:$J$251,$B$12,'Raw Data'!$L$2:$L$251,$B$13,'Raw Data'!$B$2:$B$251,">="&$B$14,'Raw Data'!$B$2:$B$251,"<="&$B$15,'Raw Data'!$K$2:$K$251,A39) -> 42
A40: West | B40: =SUMIFS('Raw Data'!$N$2:$N$251,'Raw Data'!$K$2:$K$251,$B$10,'Raw Data'!$G$2:$G$251,$B$11,'Raw Data'!$J$2:$J$251,$B$12,'Raw Data'!$L$2:$L$251,$B$13,'Raw Data'!$B$2:$B$251,">="&$B$14,'Raw Data'!$B$2:$B$251,"<="&$B$15,'Raw Data'!$K$2:$K$251,A40) -> 41408.68 | C40: =COUNTIFS('Raw Data'!$K$2:$K$251,$B$10,'Raw Data'!$G$2:$G$251,$B$11,'Raw Data'!$J$2:$J$251,$B$12,'Raw Data'!$L$2:$L$251,$B$13,'Raw Data'!$B$2:$B$251,">="&$B$14,'Raw Data'!$B$2:$B$251,"<="&$B$15,'Raw Data'!$K$2:$K$251,A40) -> 47
A43: Category | B43: Revenue | C43: Orders
A44: Appliances | B44: =SUMIFS('Raw Data'!$N$2:$N$251,'Raw Data'!$K$2:$K$251,$B$10,'Raw Data'!$G$2:$G$251,$B$11,'Raw Data'!$J$2:$J$251,$B$12,'Raw Data'!$L$2:$L$251,$B$13,'Raw Data'!$B$2:$B$251,">="&$B$14,'Raw Data'!$B$2:$B$251,"<="&$B$15,'Raw Data'!$G$2:$G$251,A44) -> 8338.74 | C44: =COUNTIFS('Raw Data'!$K$2:$K$251,$B$10,'Raw Data'!$G$2:$G$251,$B$11,'Raw Data'!$J$2:$J$251,$B$12,'Raw Data'!$L$2:$L$251,$B$13,'Raw Data'!$B$2:$B$251,">="&$B$14,'Raw Data'!$B$2:$B$251,"<="&$B$15,'Raw Data'!$G$2:$G$251,A44) -> 43
A45: Electronics | B45: =SUMIFS('Raw Data'!$N$2:$N$251,'Raw Data'!$K$2:$K$251,$B$10,'Raw Data'!$G$2:$G$251,$B$11,'Raw Data'!$J$2:$J$251,$B$12,'Raw Data'!$L$2:$L$251,$B$13,'Raw Data'!$B$2:$B$251,">="&$B$14,'Raw Data'!$B$2:$B$251,"<="&$B$15,'Raw Data'!$G$2:$G$251,A45) -> 171756.05 | C45: =COUNTIFS('Raw Data'!$K$2:$K$251,$B$10,'Raw Data'!$G$2:$G$251,$B$11,'Raw Data'!$J$2:$J$251,$B$12,'Raw Data'!$L$2:$L$251,$B$13,'Raw Data'!$B$2:$B$251,">="&$B$14,'Raw Data'!$B$2:$B$251,"<="&$B$15,'Raw Data'!$G$2:$G$251,A45) -> 131
A46: Furniture | B46: =SUMIFS('Raw Data'!$N$2:$N$251,'Raw Data'!$K$2:$K$251,$B$10,'Raw Data'!$G$2:$G$251,$B$11,'Raw Data'!$J$2:$J$251,$B$12,'Raw Data'!$L$2:$L$251,$B$13,'Raw Data'!$B$2:$B$251,">="&$B$14,'Raw Data'!$B$2:$B$251,"<="&$B$15,'Raw Data'!$G$2:$G$251,A46) -> 49097.68 | C46: =COUNTIFS('Raw Data'!$K$2:$K$251,$B$10,'Raw Data'!$G$2:$G$251,$B$11,'Raw Data'!$J$2:$J$251,$B$12,'Raw Data'!$L$2:$L$251,$B$13,'Raw Data'!$B$2:$B$251,">="&$B$14,'Raw Data'!$B$2:$B$251,"<="&$B$15,'Raw Data'!$G$2:$G$251,A46) -> 76
A49: Payment | B49: Revenue | C49: Orders
A50: Cash | B50: =SUMIFS('Raw Data'!$N$2:$N$251,'Raw Data'!$K$2:$K$251,$B$10,'Raw Data'!$G$2:$G$251,$B$11,'Raw Data'!$J$2:$J$251,$B$12,'Raw Data'!$L$2:$L$251,$B$13,'Raw Data'!$B$2:$B$251,">="&$B$14,'Raw Data'!$B$2:$B$251,"<="&$B$15,'Raw Data'!$J$2:$J$251,A50) -> 57427.79 | C50: =COUNTIFS('Raw Data'!$K$2:$K$251,$B$10,'Raw Data'!$G$2:$G$251,$B$11,'Raw Data'!$J$2:$J$251,$B$12,'Raw Data'!$L$2:$L$251,$B$13,'Raw Data'!$B$2:$B$251,">="&$B$14,'Raw Data'!$B$2:$B$251,"<="&$B$15,'Raw Data'!$J$2:$J$251,A50) -> 76
A51: Credit Card | B51: =SUMIFS('Raw Data'!$N$2:$N$251,'Raw Data'!$K$2:$K$251,$B$10,'Raw Data'!$G$2:$G$251,$B$11,'Raw Data'!$J$2:$J$251,$B$12,'Raw Data'!$L$2:$L$251,$B$13,'Raw Data'!$B$2:$B$251,">="&$B$14,'Raw Data'!$B$2:$B$251,"<="&$B$15,'Raw Data'!$J$2:$J$251,A51) -> 61447.96 | C51: =COUNTIFS('Raw Data'!$K$2:$K$251,$B$10,'Raw Data'!$G$2:$G$251,$B$11,'Raw Data'!$J$2:$J$251,$B$12,'Raw Data'!$L$2:$L$251,$B$13,'Raw Data'!$B$2:$B$251,">="&$B$14,'Raw Data'!$B$2:$B$251,"<="&$B$15,'Raw Data'!$J$2:$J$251,A51) -> 68
A52: Debit Card | B52: =SUMIFS('Raw Data'!$N$2:$N$251,'Raw Data'!$K$2:$K$251,$B$10,'Raw Data'!$G$2:$G$251,$B$11,'Raw Data'!$J$2:$J$251,$B$12,'Raw Data'!$L$2:$L$251,$B$13,'Raw Data'!$B$2:$B$251,">="&$B$14,'Raw Data'!$B$2:$B$251,"<="&$B$15,'Raw Data'!$J$2:$J$251,A52) -> 52118.31 | C52: =COUNTIFS('Raw Data'!$K$2:$K$251,$B$10,'Raw Data'!$G$2:$G$251,$B$11,'Raw Data'!$J$2:$J$251,$B$12,'Raw Data'!$L$2:$L$251,$B$13,'Raw Data'!$B$2:$B$251,">="&$B$14,'Raw Data'!$B$2:$B$251,"<="&$B$15,'Raw Data'!$J$2:$J$251,A52) -> 54
A53: PayPal | B53: =SUMIFS('Raw Data'!$N$2:$N$251,'Raw Data'!$K$2:$K$251,$B$10,'Raw Data'!$G$2:$G$251,$B$11,'Raw Data'!$J$2:$J$251,$B$12,'Raw Data'!$L$2:$L$251,$B$13,'Raw Data'!$B$2:$B$251,">="&$B$14,'Raw Data'!$B$2:$B$251,"<="&$B$15,'Raw Data'!$J$2:$J$251,A53) -> 58198.41 | C53: =COUNTIFS('Raw Data'!$K$2:$K$251,$B$10,'Raw Data'!$G$2:$G$251,$B$11,'Raw Data'!$J$2:$J$251,$B$12,'Raw Data'!$L$2:$L$251,$B$13,'Raw Data'!$B$2:$B$251,">="&$B$14,'Raw Data'!$B$2:$B$251,"<="&$B$15,'Raw Data'!$J$2:$J$251,A53) -> 52
A56: Product | B56: Revenue | C56: Rank | E56: Rank # | F56: Product (sorted) | G56: Revenue (sorted)
A57: =Analysis!B35 -> Laptop | B57: =SUMIFS('Raw Data'!$N$2:$N$251,'Raw Data'!$K$2:$K$251,$B$10,'Raw Data'!$G$2:$G$251,$B$11,'Raw Data'!$J$2:$J$251,$B$12,'Raw Data'!$L$2:$L$251,$B$13,'Raw Data'!$B$2:$B$251,">="&$B$14,'Raw Data'!$B$2:$B$251,"<="&$B$15,'Raw Data'!$F$2:$F$251,A57) -> 67499.25 | C57: =RANK(B57,$B$57:$B$66,0)+COUNTIF($B$57:B57,B57)-1 -> 1 | E57: 1 | F57: =INDEX($A$57:$A$66,MATCH(E57,$C$57:$C$66,0)) -> Laptop | G57: =INDEX($B$57:$B$66,MATCH(E57,$C$57:$C$66,0)) -> 67499.25
A58: =Analysis!B36 -> Smartphone | B58: =SUMIFS('Raw Data'!$N$2:$N$251,'Raw Data'!$K$2:$K$251,$B$10,'Raw Data'!$G$2:$G$251,$B$11,'Raw Data'!$J$2:$J$251,$B$12,'Raw Data'!$L$2:$L$251,$B$13,'Raw Data'!$B$2:$B$251,">="&$B$14,'Raw Data'!$B$2:$B$251,"<="&$B$15,'Raw Data'!$F$2:$F$251,A58) -> 67199.04 | C58: =RANK(B58,$B$57:$B$66,0)+COUNTIF($B$57:B58,B58)-1 -> 2 | E58: 2 | F58: =INDEX($A$57:$A$66,MATCH(E58,$C$57:$C$66,0)) -> Smartphone | G58: =INDEX($B$57:$B$66,MATCH(E58,$C$57:$C$66,0)) -> 67199.04
A59: =Analysis!B37 -> Headphones | B59: =SUMIFS('Raw Data'!$N$2:$N$251,'Raw Data'!$K$2:$K$251,$B$10,'Raw Data'!$G$2:$G$251,$B$11,'Raw Data'!$J$2:$J$251,$B$12,'Raw Data'!$L$2:$L$251,$B$13,'Raw Data'!$B$2:$B$251,">="&$B$14,'Raw Data'!$B$2:$B$251,"<="&$B$15,'Raw Data'!$F$2:$F$251,A59) -> 7049.53 | C59: =RANK(B59,$B$57:$B$66,0)+COUNTIF($B$57:B59,B59)-1 -> 8 | E59: 3 | F59: =INDEX($A$57:$A$66,MATCH(E59,$C$57:$C$66,0)) -> Desk | G59: =INDEX($B$57:$B$66,MATCH(E59,$C$57:$C$66,0)) -> 23399.22
A60: =Analysis!B38 -> Coffee Maker | B60: =SUMIFS('Raw Data'!$N$2:$N$251,'Raw Data'!$K$2:$K$251,$B$10,'Raw Data'!$G$2:$G$251,$B$11,'Raw Data'!$J$2:$J$251,$B$12,'Raw Data'!$L$2:$L$251,$B$13,'Raw Data'!$B$2:$B$251,">="&$B$14,'Raw Data'!$B$2:$B$251,"<="&$B$15,'Raw Data'!$F$2:$F$251,A60) -> 3119.61 | C60: =RANK(B60,$B$57:$B$66,0)+COUNTIF($B$57:B60,B60)-1 -> 10 | E60: 4 | F60: =INDEX($A$57:$A$66,MATCH(E60,$C$57:$C$66,0)) -> Monitor | G60: =INDEX($B$57:$B$66,MATCH(E60,$C$57:$C$66,0)) -> 21999.12
A61: =Analysis!B39 -> Blender | B61: =SUMIFS('Raw Data'!$N$2:$N$251,'Raw Data'!$K$2:$K$251,$B$10,'Raw Data'!$G$2:$G$251,$B$11,'Raw Data'!$J$2:$J$251,$B$12,'Raw Data'!$L$2:$L$251,$B$13,'Raw Data'!$B$2:$B$251,">="&$B$14,'Raw Data'!$B$2:$B$251,"<="&$B$15,'Raw Data'!$F$2:$F$251,A61) -> 5219.13 | C61: =RANK(B61,$B$57:$B$66,0)+COUNTIF($B$57:B61,B61)-1 -> 9 | E61: 5 | F61: =INDEX($A$57:$A$66,MATCH(E61,$C$57:$C$66,0)) -> Bookshelf | G61: =INDEX($B$57:$B$66,MATCH(E61,$C$57:$C$66,0)) -> 15298.98
A62: =Analysis!B40 -> Office Chair | B62: =SUMIFS('Raw Data'!$N$2:$N$251,'Raw Data'!$K$2:$K$251,$B$10,'Raw Data'!$G$2:$G$251,$B$11,'Raw Data'!$J$2:$J$251,$B$12,'Raw Data'!$L$2:$L$251,$B$13,'Raw Data'!$B$2:$B$251,">="&$B$14,'Raw Data'!$B$2:$B$251,"<="&$B$15,'Raw Data'!$F$2:$F$251,A62) -> 10399.48 | C62: =RANK(B62,$B$57:$B$66,0)+COUNTIF($B$57:B62,B62)-1 -> 6 | E62: 6 | F62: =INDEX($A$57:$A$66,MATCH(E62,$C$57:$C$66,0)) -> Office Chair | G62: =INDEX($B$57:$B$66,MATCH(E62,$C$57:$C$66,0)) -> 10399.48
A63: =Analysis!B41 -> Desk | B63: =SUMIFS('Raw Data'!$N$2:$N$251,'Raw Data'!$K$2:$K$251,$B$10,'Raw Data'!$G$2:$G$251,$B$11,'Raw Data'!$J$2:$J$251,$B$12,'Raw Data'!$L$2:$L$251,$B$13,'Raw Data'!$B$2:$B$251,">="&$B$14,'Raw Data'!$B$2:$B$251,"<="&$B$15,'Raw Data'!$F$2:$F$251,A63) -> 23399.22 | C63: =RANK(B63,$B$57:$B$66,0)+COUNTIF($B$57:B63,B63)-1 -> 3 | E63: 7 | F63: =INDEX($A$57:$A$66,MATCH(E63,$C$57:$C$66,0)) -> Keyboard | G63: =INDEX($B$57:$B$66,MATCH(E63,$C$57:$C$66,0)) -> 8009.11
A64: =Analysis!B42 -> Bookshelf | B64: =SUMIFS('Raw Data'!$N$2:$N$251,'Raw Data'!$K$2:$K$251,$B$10,'Raw Data'!$G$2:$G$251,$B$11,'Raw Data'!$J$2:$J$251,$B$12,'Raw Data'!$L$2:$L$251,$B$13,'Raw Data'!$B$2:$B$251,">="&$B$14,'Raw Data'!$B$2:$B$251,"<="&$B$15,'Raw Data'!$F$2:$F$251,A64) -> 15298.98 | C64: =RANK(B64,$B$57:$B$66,0)+COUNTIF($B$57:B64,B64)-1 -> 5 | E64: 8 | F64: =INDEX($A$57:$A$66,MATCH(E64,$C$57:$C$66,0)) -> Headphones | G64: =INDEX($B$57:$B$66,MATCH(E64,$C$57:$C$66,0)) -> 7049.53
A65: =Analysis!B43 -> Monitor | B65: =SUMIFS('Raw Data'!$N$2:$N$251,'Raw Data'!$K$2:$K$251,$B$10,'Raw Data'!$G$2:$G$251,$B$11,'Raw Data'!$J$2:$J$251,$B$12,'Raw Data'!$L$2:$L$251,$B$13,'Raw Data'!$B$2:$B$251,">="&$B$14,'Raw Data'!$B$2:$B$251,"<="&$B$15,'Raw Data'!$F$2:$F$251,A65) -> 21999.12 | C65: =RANK(B65,$B$57:$B$66,0)+COUNTIF($B$57:B65,B65)-1 -> 4 | E65: 9 | F65: =INDEX($A$57:$A$66,MATCH(E65,$C$57:$C$66,0)) -> Blender | G65: =INDEX($B$57:$B$66,MATCH(E65,$C$57:$C$66,0)) -> 5219.13
A66: =Analysis!B44 -> Keyboard | B66: =SUMIFS('Raw Data'!$N$2:$N$251,'Raw Data'!$K$2:$K$251,$B$10,'Raw Data'!$G$2:$G$251,$B$11,'Raw Data'!$J$2:$J$251,$B$12,'Raw Data'!$L$2:$L$251,$B$13,'Raw Data'!$B$2:$B$251,">="&$B$14,'Raw Data'!$B$2:$B$251,"<="&$B$15,'Raw Data'!$F$2:$F$251,A66) -> 8009.11 | C66: =RANK(B66,$B$57:$B$66,0)+COUNTIF($B$57:B66,B66)-1 -> 7 | E66: 10 | F66: =INDEX($A$57:$A$66,MATCH(E66,$C$57:$C$66,0)) -> Coffee Maker | G66: =INDEX($B$57:$B$66,MATCH(E66,$C$57:$C$66,0)) -> 3119.61
A69: Selected-view KPIs
A70: Revenue | B70: =SUMIFS('Raw Data'!$N$2:$N$251,'Raw Data'!$K$2:$K$251,$B$10,'Raw Data'!$G$2:$G$251,$B$11,'Raw Data'!$J$2:$J$251,$B$12,'Raw Data'!$L$2:$L$251,$B$13,'Raw Data'!$B$2:$B$251,">="&$B$14,'Raw Data'!$B$2:$B$251,"<="&$B$15) -> 229192.47
A71: Orders | B71: =COUNTIFS('Raw Data'!$K$2:$K$251,$B$10,'Raw Data'!$G$2:$G$251,$B$11,'Raw Data'!$J$2:$J$251,$B$12,'Raw Data'!$L$2:$L$251,$B$13,'Raw Data'!$B$2:$B$251,">="&$B$14,'Raw Data'!$B$2:$B$251,"<="&$B$15) -> 250
A72: Units | B72: =SUMIFS('Raw Data'!$H$2:$H$251,'Raw Data'!$K$2:$K$251,$B$10,'Raw Data'!$G$2:$G$251,$B$11,'Raw Data'!$J$2:$J$251,$B$12,'Raw Data'!$L$2:$L$251,$B$13,'Raw Data'!$B$2:$B$251,">="&$B$14,'Raw Data'!$B$2:$B$251,"<="&$B$15) -> 753
A73: Avg order | B73: =IF(B71=0,0,B70/B71) -> 916.76988
A74: Share of total revenue | B74: =IF(Analysis!B24=0,0,B70/Analysis!B24) -> 1
A75: Filter state | B75: =IF(AND(Dashboard!B11="All",Dashboard!E11="All",Dashboard!H11="All",Dashboard!K11="All",Dashboard!N11<=Analysis!B8,Dashboard!Q11>=Analysis!B9),"Full dataset (no filters)","Filtered view") -> Full dataset (no filters)
